Workbook

Sheet START
A1: DRACULA BOOK — 100 TITLURI / 300 EDIȚII
A2: Actualizat la | B2: 46288 | C2: Plan condiționat de capacitate și buget; nu dovadă de publicare.
A3: Titluri distincte planificate | B3: =COUNTA(Catalog_100!A2:A101) -> 100 | C3: 17 proiecte existente + 83 concepte noi.
A4: Manuscrise candidate existente | B4: =COUNTIF(Catalog_100!F2:F101,"Fond") -> 17 | C4: 14 EN + 3 RO; Signal incomplet.
A5: Titluri noi de scris | B5: =COUNTIF(Catalog_100!F2:F101,"Nou") -> 83 | C5: Titlurile și premisele sunt propuse, nu manuscrise finalizate.
A6: Ediții lingvistice planificate | B6: =COUNTA(Editii_300!A2:A301) -> 300 | C6: 100 EN + 100 RO + 100 DE.
A7: Ediții publicate cu dovezi complete | B7: =SUM(Editii_300!X2:X301) -> 0 | C7: Stare Publicat + aprobator + dată + URL + checksum + drepturi confirmate.
A8: Titluri încheiate în toate 3 limbile | B8: =SUM(Catalog_100!T2:T101) -> 0 | C8: Niciun titlu nu este marcat final doar pentru existența unui fișier.
A9: Cuvinte master planificate | B9: =SUM(Catalog_100!I2:I101) -> 5419000 | C9: Lungimi de lucru; nu cuvinte deja aprobate.
A10: Echivalent cuvinte de tradus | B10: =B9*2 -> 10838000 | C10: 200 operațiuni; 3 RO→EN, 97 EN→RO, 100 spre DE.
A11: Buget bază cu rezervă EUR | B11: =Buget!G18 -> 1532203.2 | C11: Ipoteze de externalizare, nu ofertă; exclude taxele aplicabile.
A12: Necesar echivalent execuție | B12: =Capacitate!H11 -> 203 | C12: Adăugați coordonare/design; nu este personal existent.
A14: CUM SE FOLOSEȘTE
A15: 1. Audit_17 | B15: Verificare | C15: Confirmați masterul, autorul, titlul, limba, drepturile și distinctivitatea.
A16: 2. Catalog_100 | B16: Plan editorial | C16: Desemnați autor/editor; detaliați fiecare premisă într-un brief de 2–4 pagini.
A17: 3. Editii_300 | B17: Progres real | C17: Actualizați starea și aprobările. Publicat fără probe nu crește indicatorul verificat.
A18: 4. Capacitate / Buget | B18: Ipoteze editabile | C18: Celulele albastre sunt ipoteze; înlocuiți cu timpi și oferte măsurate.
A19: 5. Scenarii | B19: Nu prognoze | C19: Modelul de abonament este context comercial, nu modificare a site-ului.
A20: 6. Surse | B20: Trasabilitate | C20: Anii datelor diferă; nu adunați piețe cu metodologii diferite.
A21: 7. Calendar | B21: Scenariu accelerat | C21: Comparați săptămânal țintele cu realizatul; nu schimbați starea pentru a bifa data.
A23: LIMITĂ DE AUDIT | B23: Important | C23: Inventar și structură plus eșantioane, nu lectură literară integrală a 17 manuscrise.
A24: FIȘIERE ORIGINALE | B24: Nemodificate | C24: Acest registru nu mută și nu rescrie cărțile și nu modifică site-ul.
A25: INFORMAȚII LIPSĂ | B25: De furnizat | C25: Buget aprobat, echipă disponibilă, vânzări actuale, dovezi ISBN/ASIN/linkuri și drepturi.

Sheet Catalog_100
A1: WorkID | B1: Colecție | C1: Saga | D1: Volum | E1: Titlu de lucru / existent | F1: Bază | G1: Sursă | H1: Stare inițială | I1: Țintă cuvinte | J1: Master EN țintă | K1: Traduceri țintă | L1: QA țintă | M1: Lansare trilingvă țintă | N1: Lot | O1: Responsabil | P1: Gen / format | Q1: Premisă de lucru | R1: Observații | S1: Ediții verificate | T1: Titlu trilingv realizat
A2: DB-001 | B2: NOIR | C2: Cronicile Transilvaniei | D2: 1 | E2: Umbra Trandafirului Negru | F2: Fond | G2: RO | H2: Manuscris candidat — nevalidat editorial | I2: 60000 | J2: 46298 | K2: 46301 | L2: 46303 | M2: 46305 | N2: PILOT | O2: De contractat / desemnat | P2: Roman istoric-gotic | Q2: Vlad, Bran și o conspirație; de stabilit cronologia istoric-fantastică. | R2: Materiale de lucru și profiluri înaintea romanului; cronologie de corelat cu site-ul. | S2: =COUNTIFS(Editii_300!$B$2:$B$301,A2,Editii_300!$X$2:$X$301,1) -> 0 | T2: =IF(S2=3,1,0) -> 0
A3: DB-002 | B3: NOIR | C3: Cronicile Transilvaniei | D3: 2 | E3: Marienburg: Sigiliul Fecioarei | F3: Fond | G3: RO | H3: Manuscris candidat — nevalidat editorial | I3: 70000 | J3: 46305 | K3: 46315 | L3: 46317 | M3: 46319 | N3: FOND EXISTENT | O3: De contractat / desemnat | P3: Roman istoric-gotic | Q3: Anchetă la Feldioara; legătura dintre două epoci. | R3: Circa 76,8k cuvinte brute, nu 85–95k confirmate; marcaje și epoci de verificat. | S3: =COUNTIFS(Editii_300!$B$2:$B$301,A3,Editii_300!$X$2:$X$301,1) -> 0 | T3: =IF(S3=3,1,0) -> 0
A4: DB-003 | B4: NOIR | C4: Cronicile Transilvaniei | D4: 3 | E4: Sânge și Sare la Schäßburg | F4: Fond | G4: RO | H4: Manuscris candidat — nevalidat editorial | I4: 80000 | J4: 46305 | K4: 46315 | L4: 46317 | M4: 46319 | N4: FOND EXISTENT | O4: De contractat / desemnat | P4: Roman istoric-gotic | Q4: Titlu de reconciliat cu CIVITAS SEX – Legământul de Sare. | R4: Titlul interior diferă de copertă/site; prefată de proces AI și note de eliminat. | S4: =COUNTIFS(Editii_300!$B$2:$B$301,A4,Editii_300!$X$2:$X$301,1) -> 0 | T4: =IF(S4=3,1,0) -> 0
A5: DB-004 | B5: NOIR | C5: Cronicile Transilvaniei | D5: 4 | E5: The Bellmaker of Brașov | F5: Nou | G5: EN | H5: Concept propus; nescris | I5: 60000 | J5: 46318 | K5: 46336 | L5: 46338 | M5: 46340 | N5: LOT C | O5: De contractat / desemnat | P5: Roman istoric-gotic | Q5: Un clopot nou anunță crime înainte să fie comise. | S5: =COUNTIFS(Editii_300!$B$2:$B$301,A5,Editii_300!$X$2:$X$301,1) -> 0 | T5: =IF(S5=3,1,0) -> 0
A6: DB-005 | B6: NOIR | C6: Cronicile Transilvaniei | D6: 5 | E6: The Sibiu Testament | F6: Nou | G6: EN | H6: Concept propus; nescris | I6: 60000 | J6: 46318 | K6: 46336 | L6: 46338 | M6: 46340 | N6: LOT C | O6: De contractat / desemnat | P6: Roman istoric-gotic | Q6: O moștenire schimbă mâinile de fiecare dată când moare un martor. | S6: =COUNTIFS(Editii_300!$B$2:$B$301,A6,Editii_300!$X$2:$X$301,1) -> 0 | T6: =IF(S6=3,1,0) -> 0
A7: DB-006 | B7: NOIR | C7: Cronicile Transilvaniei | D7: 6 | E7: The Bistrița Bride | F7: Nou | G7: EN | H7: Concept propus; nescris | I7: 60000 | J7: 46318 | K7: 46336 | L7: 46338 | M7: 46340 | N7: LOT C | O7: De contractat / desemnat | P7: Roman istoric-gotic | Q7: O nuntă politică ascunde dispariția miresei din registrul parohial. | S7: =COUNTIFS(Editii_300!$B$2:$B$301,A7,Editii_300!$X$2:$X$301,1) -> 0 | T7: =IF(S7=3,1,0) -> 0
A8: DB-007 | B8: NOIR | C8: Cronicile Transilvaniei | D8: 7 | E8: The Locksmith of Sighișoara | F8: Nou | G8: EN | H8: Concept propus; nescris | I8: 60000 | J8: 46318 | K8: 46336 | L8: 46338 | M8: 46340 | N8: LOT C | O8: De contractat / desemnat | P8: Roman istoric-gotic | Q8: Un meșter recunoaște propria cheie într-o cameră sigilată. | S8: =COUNTIFS(Editii_300!$B$2:$B$301,A8,Editii_300!$X$2:$X$301,1) -> 0 | T8: =IF(S8=3,1,0) -> 0
A9: DB-008 | B9: NOIR | C9: Cronicile Transilvaniei | D9: 8 | E9: The Alba Iulia Cipher | F9: Nou | G9: EN | H9: Concept propus; nescris | I9: 60000 | J9: 46318 | K9: 46336 | L9: 46338 | M9: 46340 | N9: LOT C | O9: De contractat / desemnat | P9: Roman istoric-gotic | Q9: O traducătoare descoperă un verdict ascuns într-o cronică. | S9: =COUNTIFS(Editii_300!$B$2:$B$301,A9,Editii_300!$X$2:$X$301,1) -> 0 | T9: =IF(S9=3,1,0) -> 0
A10: DB-009 | B10: NOIR | C10: Cronicile Transilvaniei | D10: 9 | E10: The Winter Court of Bran | F10: Nou | G10: EN | H10: Concept propus; nescris | I10: 60000 | J10: 46318 | K10: 46336 | L10: 46338 | M10: 46340 | N10: LOT C | O10: De contractat / desemnat | P10: Roman istoric-gotic | Q10: Un asediu de iarnă transformă aliații în suspecți. | S10: =COUNTIFS(Editii_300!$B$2:$B$301,A10,Editii_300!$X$2:$X$301,1) -> 0 | T10: =IF(S10=3,1,0) -> 0
A11: DB-010 | B11: NOIR | C11: Cronicile Transilvaniei | D11: 10 | E11: The Last Black Rose | F11: Nou | G11: EN | H11: Concept propus; nescris | I11: 60000 | J11: 46318 | K11: 46336 | L11: 46338 | M11: 46340 | N11: LOT C | O11: De contractat / desemnat | P11: Roman istoric-gotic | Q11: Ultimul caz închide arcul conspirației fără a repeta primul volum. | S11: =COUNTIFS(Editii_300!$B$2:$B$301,A11,Editii_300!$X$2:$X$301,1) -> 0 | T11: =IF(S11=3,1,0) -> 0
A12: DB-011 | B12: NOIR | C12: Carpathian Cold Cases | D12: 1 | E12: The Witness Beneath the Ice | F12: Nou | G12: EN | H12: Concept propus; nescris | I12: 55000 | J12: 46311 | K12: 46329 | L12: 46331 | M12: 46333 | N12: LOT B | O12: De contractat / desemnat | P12: Thriller contemporan | Q12: Topirea unui lac readuce o dispariție și un martor mincinos. | S12: =COUNTIFS(Editii_300!$B$2:$B$301,A12,Editii_300!$X$2:$X$301,1) -> 0 | T12: =IF(S12=3,1,0) -> 0
A13: DB-012 | B13: NOIR | C13: Carpathian Cold Cases | D13: 2 | E13: The Missing Carriage | F13: Nou | G13: EN | H13: Concept propus; nescris | I13: 55000 | J13: 46311 | K13: 46329 | L13: 46331 | M13: 46333 | N13: LOT B | O13: De contractat / desemnat | P13: Thriller contemporan | Q13: O înregistrare feroviară dovedește existența unui vagon dispărut. | S13: =COUNTIFS(Editii_300!$B$2:$B$301,A13,Editii_300!$X$2:$X$301,1) -> 0 | T13: =IF(S13=3,1,0) -> 0
A14: DB-013 | B14: NOIR | C14: Carpathian Cold Cases | D14: 3 | E14: The Village That Forgot Her | F14: Nou | G14: EN | H14: Concept propus; nescris | I14: 55000 | J14: 46311 | K14: 46329 | L14: 46331 | M14: 46333 | N14: LOT B | O14: De contractat / desemnat | P14: Thriller contemporan | Q14: O arhivistă găsește aceeași femeie ștearsă din toate fotografiile. | S14: =COUNTIFS(Editii_300!$B$2:$B$301,A14,Editii_300!$X$2:$X$301,1) -> 0 | T14: =IF(S14=3,1,0) -> 0
A15: DB-014 | B15: NOIR | C15: Carpathian Cold Cases | D15: 4 | E15: The Funeral Guest | F15: Nou | G15: EN | H15: Concept propus; nescris | I15: 55000 | J15: 46311 | K15: 46329 | L15: 46331 | M15: 46333 | N15: LOT B | O15: De contractat / desemnat | P15: Thriller contemporan | Q15: Un necunoscut lasă o probă la înmormântarea unei anchetatoare. | S15: =COUNTIFS(Editii_300!$B$2:$B$301,A15,Editii_300!$X$2:$X$301,1) -> 0 | T15: =IF(S15=3,1,0) -> 0
A16: DB-015 | B16: NOIR | C16: Carpathian Cold Cases | D16: 5 | E16: The Quarry Silence | F16: Nou | G16: EN | H16: Concept propus; nescris | I16: 55000 | J16: 46311 | K16: 46329 | L16: 46331 | M16: 46333 | N16: LOT B | O16: De contractat / desemnat | P16: Thriller contemporan | Q16: O carieră dezafectată amenință pactul unui oraș prosper. | S16: =COUNTIFS(Editii_300!$B$2:$B$301,A16,Editii_300!$X$2:$X$301,1) -> 0 | T16: =IF(S16=3,1,0) -> 0
... A36: DB-035 | B36: NOIR | C36: The Borderland Files | D36: 5 | E36: The Bridge at First Snow | F36: Nou | G36: EN | H36: Concept propus; nescris | I36: 35000 | J36: 46304 | K36: 46322 | L36: 46324 | M36: 46326 | N36: LOT A | O36: De contractat / desemnat | P36: Roman scurt de mister | Q36: O punte izolată adună trei versiuni incompatibile ale aceleiași nopți. | S36: =COUNTIFS(Editii_300!$B$2:$B$301,A36,Editii_300!$X$2:$X$301,1) -> 0 | T36: =IF(S36=3,1,0) -> 0
A37: DB-036 | B37: AMORIS | C37: Alex Damian | D37: 1 | E37: Beneath the Skin of the Sea | F37: Fond | G37: EN | H37: Manuscris candidat — nevalidat editorial | I37: 80000 | J37: 46298 | K37: 46301 | L37: 46303 | M37: 46305 | N37: PILOT | O37: De contractat / desemnat | P37: Romance de aventură | Q37: Alex și Elena; epavă grecească, vulnerabilitate și reconstrucție. | R37: Raportul intern de 9,87/10 nu dovedește recenzie independentă sau publicare. | S37: =COUNTIFS(Editii_300!$B$2:$B$301,A37,Editii_300!$X$2:$X$301,1) -> 0 | T37: =IF(S37=3,1,0) -> 0
A38: DB-037 | B38: AMORIS | C38: Alex Damian | D38: 2 | E38: Shadows in the Port | F38: Fond | G38: EN | H38: Manuscris candidat — nevalidat editorial | I38: 90000 | J38: 46305 | K38: 46315 | L38: 46317 | M38: 46319 | N38: FOND EXISTENT | O38: De contractat / desemnat | P38: Romance de aventură | Q38: De verificat distinctivitatea față de Beneath; rescris ca sequel dacă este variantă. | R38: Alex/Elena și început apropiat de Beneath; verificare sequel vs rescriere; heading 5 neidentificat. | S38: =COUNTIFS(Editii_300!$B$2:$B$301,A38,Editii_300!$X$2:$X$301,1) -> 0 | T38: =IF(S38=3,1,0) -> 0
A39: DB-038 | B39: AMORIS | C39: Alex Damian | D39: 3 | E39: The Last Sunset in Santorini | F39: Nou | G39: EN | H39: Concept propus; nescris | I39: 60000 | J39: 46318 | K39: 46336 | L39: 46338 | M39: 46340 | N39: LOT C | O39: De contractat / desemnat | P39: Romance de aventură | Q39: Un proiect de salvare amenință promisiunea făcută pe uscat. | S39: =COUNTIFS(Editii_300!$B$2:$B$301,A39,Editii_300!$X$2:$X$301,1) -> 0 | T39: =IF(S39=3,1,0) -> 0
A40: DB-039 | B40: AMORIS | C40: Alex Damian | D40: 4 | E40: Breath of the Deep | F40: Nou | G40: EN | H40: Concept propus; nescris | I40: 60000 | J40: 46318 | K40: 46336 | L40: 46338 | M40: 46340 | N40: LOT C | O40: De contractat / desemnat | P40: Romance de aventură | Q40: O epavă readuce o datorie din trecutul naval. | S40: =COUNTIFS(Editii_300!$B$2:$B$301,A40,Editii_300!$X$2:$X$301,1) -> 0 | T40: =IF(S40=3,1,0) -> 0
A41: DB-040 | B41: AMORIS | C41: Alex Damian | D41: 5 | E41: The Woman in the Blue Light | F41: Nou | G41: EN | H41: Concept propus; nescris | I41: 60000 | J41: 46318 | K41: 46336 | L41: 46338 | M41: 46340 | N41: LOT C | O41: De contractat / desemnat | P41: Romance de aventură | Q41: O dispariție obligă o jurnalistă și un scafandru să coopereze. | S41: =COUNTIFS(Editii_300!$B$2:$B$301,A41,Editii_300!$X$2:$X$301,1) -> 0 | T41: =IF(S41=3,1,0) -> 0
A42: DB-041 | B42: AMORIS | C42: Alex Damian | D42: 6 | E42: The Island Without Names | F42: Nou | G42: EN | H42: Concept propus; nescris | I42: 60000 | J42: 46318 | K42: 46336 | L42: 46338 | M42: 46340 | N42: LOT C | O42: De contractat / desemnat | P42: Romance de aventură | Q42: O furtună testează încrederea unei echipe izolate. | S42: =COUNTIFS(Editii_300!$B$2:$B$301,A42,Editii_300!$X$2:$X$301,1) -> 0 | T42: =IF(S42=3,1,0) -> 0
A43: DB-042 | B43: AMORIS | C43: Alex Damian | D43: 7 | E43: Coral Hearts | F43: Nou | G43: EN | H43: Concept propus; nescris | I43: 60000 | J43: 46318 | K43: 46336 | L43: 46338 | M43: 46340 | N43: LOT C | O43: De contractat / desemnat | P43: Romance de aventură | Q43: O expediție ecologică pune iubirea și ambiția în conflict. | S43: =COUNTIFS(Editii_300!$B$2:$B$301,A43,Editii_300!$X$2:$X$301,1) -> 0 | T43: =IF(S43=3,1,0) -> 0
A44: DB-043 | B44: AMORIS | C44: Alex Damian | D44: 8 | E44: Beneath the Salt Stars | F44: Nou | G44: EN | H44: Concept propus; nescris | I44: 60000 | J44: 46318 | K44: 46336 | L44: 46338 | M44: 46340 | N44: LOT C | O44: De contractat / desemnat | P44: Romance de aventură | Q44: O iubire veche cere un adevăr pe care nimeni nu l-a spus. | S44: =COUNTIFS(Editii_300!$B$2:$B$301,A44,Editii_300!$X$2:$X$301,1) -> 0 | T44: =IF(S44=3,1,0) -> 0
A45: DB-044 | B45: AMORIS | C45: Alex Damian | D45: 9 | E45: Tidebound | F45: Nou | G45: EN | H45: Concept propus; nescris | I45: 60000 | J45: 46318 | K45: 46336 | L45: 46338 | M45: 46340 | N45: LOT C | O45: De contractat / desemnat | P45: Romance de aventură | Q45: Salvarea unui vas schimbă planul unei vieți împreună. | S45: =COUNTIFS(Editii_300!$B$2:$B$301,A45,Editii_300!$X$2:$X$301,1) -> 0 | T45: =IF(S45=3,1,0) -> 0
A46: DB-045 | B46: AMORIS | C46: Alex Damian | D46: 10 | E46: The Echo Below | F46: Nou | G46: EN | H46: Concept propus; nescris | I46: 60000 | J46: 46318 | K46: 46336 | L46: 46338 | M46: 46340 | N46: LOT C | O46: De contractat / desemnat | P46: Romance de aventură | Q46: Un secret de familie încheie arcul lui Alex printr-o alegere ireversibilă. | S46: =COUNTIFS(Editii_300!$B$2:$B$301,A46,Editii_300!$X$2:$X$301,1) -> 0 | T46: =IF(S46=3,1,0) -> 0
A47: DB-046 | B47: AMORIS | C47: Isabella Morgan / Rue des Âmes | D47: 1 | E47: Hotelul din Rue des Âmes | F47: Fond | G47: EN | H47: Manuscris candidat — nevalidat editorial | I47: 85000 | J47: 46298 | K47: 46301 | L47: 46303 | M47: 46305 | N47: PILOT | O47: De contractat / desemnat | P47: Romance contemporan | Q47: Manuscris EN; Isabella și scrisorile unui hotel din Paris. | R47: Folderul V1 conține copie identică a Aurora 1; heading CHAPTER 11 neidentificat; nu se deduce automat lipsa prozei. | S47: =COUNTIFS(Editii_300!$B$2:$B$301,A47,Editii_300!$X$2:$X$301,1) -> 0 | T47: =IF(S47=3,1,0) -> 0
A48: DB-047 | B48: AMORIS | C48: Isabella Morgan / Rue des Âmes | D48: 2 | E48: The Magenta Letters | F48: Nou | G48: EN | H48: Concept propus; nescris | I48: 60000 | J48: 46325 | K48: 46343 | L48: 46345 | M48: 46347 | N48: LOT D | O48: De contractat / desemnat | P48: Romance contemporan | Q48: Promisiunea din finalul existent: povestea lui Margaux, în universul comun. | S48: =COUNTIFS(Editii_300!$B$2:$B$301,A48,Editii_300!$X$2:$X$301,1) -> 0 | T48: =IF(S48=3,1,0) -> 0
A49: DB-048 | B49: AMORIS | C49: Isabella Morgan / Rue des Âmes | D49: 3 | E49: Coffee at the Edge of the World | F49: Nou | G49: EN | H49: Concept propus; nescris | I49: 60000 | J49: 46325 | K49: 46343 | L49: 46345 | M49: 46347 | N49: LOT D | O49: De contractat / desemnat | P49: Romance contemporan | Q49: Lisabona; o întâlnire schimbă definiția succesului. | S49: =COUNTIFS(Editii_300!$B$2:$B$301,A49,Editii_300!$X$2:$X$301,1) -> 0 | T49: =IF(S49=3,1,0) -> 0
A50: DB-049 | B50: AMORIS | C50: Isabella Morgan / Rue des Âmes | D50: 4 | E50: Under the Tokyo Sky | F50: Nou | G50: EN | H50: Concept propus; nescris | I50: 60000 | J50: 46325 | K50: 46343 | L50: 46345 | M50: 46347 | N50: LOT D | O50: De contractat / desemnat | P50: Romance contemporan | Q50: Doi profesioniști aleg între reputație și o relație imposibil de ascuns. | S50: =COUNTIFS(Editii_300!$B$2:$B$301,A50,Editii_300!$X$2:$X$301,1) -> 0 | T50: =IF(S50=3,1,0) -> 0
A51: DB-050 | B51: AMORIS | C51: Isabella Morgan / Rue des Âmes | D51: 5 | E51: Vienna After Hours | F51: Nou | G51: EN | H51: Concept propus; nescris | I51: 60000 | J51: 46325 | K51: 46343 | L51: 46345 | M51: 46347 | N51: LOT D | O51: De contractat / desemnat | P51: Romance contemporan | Q51: Un concert ratat deschide o a doua șansă. | S51: =COUNTIFS(Editii_300!$B$2:$B$301,A51,Editii_300!$X$2:$X$301,1) -> 0 | T51: =IF(S51=3,1,0) -> 0
A52: DB-051 | B52: AMORIS | C52: Isabella Morgan / Rue des Âmes | D52: 6 | E52: The Woman on Charles Bridge | F52: Nou | G52: EN | H52: Concept propus; nescris | I52: 60000 | J52: 46325 | K52: 46343 | L52: 46345 | M52: 46347 | N52: LOT D | O52: De contractat / desemnat | P52: Romance contemporan | Q52: O conferință din Praga readuce un secret de familie. | S52: =COUNTIFS(Editii_300!$B$2:$B$301,A52,Editii_300!$X$2:$X$301,1) -> 0 | T52: =IF(S52=3,1,0) -> 0
A53: DB-052 | B53: AMORIS | C53: Isabella Morgan / Rue des Âmes | D53: 7 | E53: The Marrakech Letter | F53: Nou | G53: EN | H53: Concept propus; nescris | I53: 60000 | J53: 46325 | K53: 46343 | L53: 46345 | M53: 46347 | N53: LOT D | O53: De contractat / desemnat | P53: Romance contemporan | Q53: O scrisoare schimbă cine are dreptul să spună o poveste. | S53: =COUNTIFS(Editii_300!$B$2:$B$301,A53,Editii_300!$X$2:$X$301,1) -> 0 | T53: =IF(S53=3,1,0) -> 0
A54: DB-053 | B54: AMORIS | C54: Isabella Morgan / Rue des Âmes | D54: 8 | E54: Flight Over Rome | F54: Nou | G54: EN | H54: Concept propus; nescris | I54: 60000 | J54: 46325 | K54: 46343 | L54: 46345 | M54: 46347 | N54: LOT D | O54: De contractat / desemnat | P54: Romance contemporan | Q54: Un zbor anulat obligă doi rivali să împartă o călătorie. | S54: =COUNTIFS(Editii_300!$B$2:$B$301,A54,Editii_300!$X$2:$X$301,1) -> 0 | T54: =IF(S54=3,1,0) -> 0
A55: DB-054 | B55: AMORIS | C55: Isabella Morgan / Rue des Âmes | D55: 9 | E55: Shadows of Buenos Aires | F55: Nou | G55: EN | H55: Concept propus; nescris | I55: 60000 | J55: 46325 | K55: 46343 | L55: 46345 | M55: 46347 | N55: LOT D | O55: De contractat / desemnat | P55: Romance contemporan | Q55: Dans, încredere și o alegere între plecare și apartenență. | S55: =COUNTIFS(Editii_300!$B$2:$B$301,A55,Editii_300!$X$2:$X$301,1) -> 0 | T55: =IF(S55=3,1,0) -> 0
A56: DB-055 | B56: AMORIS | C56: Isabella Morgan / Rue des Âmes | D56: 10 | E56: The Singapore Window | F56: Nou | G56: EN | H56: Concept propus; nescris | I56: 60000 | J56: 46325 | K56: 46343 | L56: 46345 | M56: 46347 | N56: LOT D | O56: De contractat / desemnat | P56: Romance contemporan | Q56: O decizie profesională deschide ultima etapă a arcului emoțional. | S56: =COUNTIFS(Editii_300!$B$2:$B$301,A56,Editii_300!$X$2:$X$301,1) -> 0 | T56: =IF(S56=3,1,0) -> 0
A57: DB-056 | B57: AMORIS | C57: Aegean Second Chances | D57: 1 | E57: The Bookshop by the Harbour | F57: Nou | G57: EN | H57: Concept propus; nescris | I57: 55000 | J57: 46311 | K57: 46329 | L57: 46331 | M57: 46333 | N57: LOT B | O57: De contractat / desemnat | P57: Romance independent conectat | Q57: O librară și un restaurator trebuie să salveze același spațiu. | S57: =COUNTIFS(Editii_300!$B$2:$B$301,A57,Editii_300!$X$2:$X$301,1) -> 0 | T57: =IF(S57=3,1,0) -> 0
A58: DB-057 | B58: AMORIS | C58: Aegean Second Chances | D58: 2 | E58: The Olive Harvest | F58: Nou | G58: EN | H58: Concept propus; nescris | I58: 55000 | J58: 46311 | K58: 46329 | L58: 46331 | M58: 46333 | N58: LOT B | O58: De contractat / desemnat | P58: Romance independent conectat | Q58: Foști rivali împart o recoltă și o datorie de familie. | S58: =COUNTIFS(Editii_300!$B$2:$B$301,A58,Editii_300!$X$2:$X$301,1) -> 0 | T58: =IF(S58=3,1,0) -> 0
A59: DB-058 | B59: AMORIS | C59: Aegean Second Chances | D59: 3 | E59: One Summer, Two Keys | F59: Nou | G59: EN | H59: Concept propus; nescris | I59: 55000 | J59: 46311 | K59: 46329 | L59: 46331 | M59: 46333 | N59: LOT B | O59: De contractat / desemnat | P59: Romance independent conectat | Q59: Doi moștenitori primesc cheia aceleiași case. | S59: =COUNTIFS(Editii_300!$B$2:$B$301,A59,Editii_300!$X$2:$X$301,1) -> 0 | T59: =IF(S59=3,1,0) -> 0
... A71: DB-070 | B71: AMORIS | C71: Midnight Letters | D71: 5 | E71: Home Before the Snow | F71: Nou | G71: EN | H71: Concept propus; nescris | I71: 35000 | J71: 46304 | K71: 46322 | L71: 46324 | M71: 46326 | N71: LOT A | O71: De contractat / desemnat | P71: Roman scurt romantic | Q71: O întoarcere forțată redeschide o relație și un atelier. | S71: =COUNTIFS(Editii_300!$B$2:$B$301,A71,Editii_300!$X$2:$X$301,1) -> 0 | T71: =IF(S71=3,1,0) -> 0
A72: DB-071 | B72: MYTHICA | C72: Saga Celor Zece Coroane | D72: 1 | E72: The Northern Crown | F72: Fond | G72: EN | H72: Manuscris candidat — nevalidat editorial | I72: 95000 | J72: 46305 | K72: 46315 | L72: 46317 | M72: 46319 | N72: FOND EXISTENT | O72: De contractat / desemnat | P72: Fantasy epic | Q72: Primul manuscris; de armonizat promisiunea volumului 2. | R72: Finalul anunță The Eastern Sands; planul arhivat numește vol.2 The Crown of Waters. | S72: =COUNTIFS(Editii_300!$B$2:$B$301,A72,Editii_300!$X$2:$X$301,1) -> 0 | T72: =IF(S72=3,1,0) -> 0
A73: DB-072 | B73: MYTHICA | C73: Saga Celor Zece Coroane | D73: 2 | E73: The Crown of Waters | F73: Nou | G73: EN | H73: Concept propus; nescris | I73: 75000 | J73: 46325 | K73: 46343 | L73: 46345 | M73: 46347 | N73: LOT D | O73: De contractat / desemnat | P73: Fantasy epic | Q73: Titlu din planul existent; conflict între putere și alianțe maritime. | S73: =COUNTIFS(Editii_300!$B$2:$B$301,A73,Editii_300!$X$2:$X$301,1) -> 0 | T73: =IF(S73=3,1,0) -> 0
A74: DB-073 | B74: MYTHICA | C74: Saga Celor Zece Coroane | D74: 3 | E74: The Crown of the Sun | F74: Nou | G74: EN | H74: Concept propus; nescris | I74: 75000 | J74: 46325 | K74: 46350 | L74: 46352 | M74: 46354 | N74: LOT E | O74: De contractat / desemnat | P74: Fantasy epic | Q74: Titlu din plan; legitimarea puterii cere un sacrificiu public. | S74: =COUNTIFS(Editii_300!$B$2:$B$301,A74,Editii_300!$X$2:$X$301,1) -> 0 | T74: =IF(S74=3,1,0) -> 0
A75: DB-074 | B75: MYTHICA | C75: Saga Celor Zece Coroane | D75: 4 | E75: The Crown of Stone | F75: Nou | G75: EN | H75: Concept propus; nescris | I75: 75000 | J75: 46325 | K75: 46350 | L75: 46352 | M75: 46354 | N75: LOT E | O75: De contractat / desemnat | P75: Fantasy epic | Q75: Titlu din plan; un regat fortificat își negociază loialitatea. | S75: =COUNTIFS(Editii_300!$B$2:$B$301,A75,Editii_300!$X$2:$X$301,1) -> 0 | T75: =IF(S75=3,1,0) -> 0
A76: DB-075 | B76: MYTHICA | C76: Saga Celor Zece Coroane | D76: 5 | E76: The Crown of the Forest | F76: Nou | G76: EN | H76: Concept propus; nescris | I76: 75000 | J76: 46325 | K76: 46350 | L76: 46352 | M76: 46354 | N76: LOT E | O76: De contractat / desemnat | P76: Fantasy epic | Q76: Titlu din plan; expansiunea politică amenință echilibrul magic. | S76: =COUNTIFS(Editii_300!$B$2:$B$301,A76,Editii_300!$X$2:$X$301,1) -> 0 | T76: =IF(S76=3,1,0) -> 0
A77: DB-076 | B77: MYTHICA | C77: Saga Celor Zece Coroane | D77: 6 | E77: The Crown of Wisdom | F77: Nou | G77: EN | H77: Concept propus; nescris | I77: 75000 | J77: 46325 | K77: 46350 | L77: 46352 | M77: 46354 | N77: LOT E | O77: De contractat / desemnat | P77: Fantasy epic | Q77: Titlu din plan; cunoașterea devine moneda alianțelor. | S77: =COUNTIFS(Editii_300!$B$2:$B$301,A77,Editii_300!$X$2:$X$301,1) -> 0 | T77: =IF(S77=3,1,0) -> 0
A78: DB-077 | B78: MYTHICA | C78: Saga Celor Zece Coroane | D78: 7 | E78: The Dark Crown | F78: Nou | G78: EN | H78: Concept propus; nescris | I78: 75000 | J78: 46325 | K78: 46350 | L78: 46352 | M78: 46354 | N78: LOT E | O78: De contractat / desemnat | P78: Fantasy epic | Q78: Titlu din plan; antagonistul oferă o soluție moralmente imposibilă. | S78: =COUNTIFS(Editii_300!$B$2:$B$301,A78,Editii_300!$X$2:$X$301,1) -> 0 | T78: =IF(S78=3,1,0) -> 0
A79: DB-078 | B79: MYTHICA | C79: Saga Celor Zece Coroane | D79: 8 | E79: The Crown of Light | F79: Nou | G79: EN | H79: Concept propus; nescris | I79: 75000 | J79: 46325 | K79: 46350 | L79: 46352 | M79: 46354 | N79: LOT E | O79: De contractat / desemnat | P79: Fantasy epic | Q79: Titlu din plan; victoria aparentă dezvăluie costul unirii. | S79: =COUNTIFS(Editii_300!$B$2:$B$301,A79,Editii_300!$X$2:$X$301,1) -> 0 | T79: =IF(S79=3,1,0) -> 0
A80: DB-079 | B80: MYTHICA | C80: Saga Celor Zece Coroane | D80: 9 | E80: The Crown of Unity | F80: Nou | G80: EN | H80: Concept propus; nescris | I80: 75000 | J80: 46325 | K80: 46350 | L80: 46352 | M80: 46354 | N80: LOT E | O80: De contractat / desemnat | P80: Fantasy epic | Q80: Titlu din plan; alianța trebuie să supraviețuiască propriilor contradicții. | S80: =COUNTIFS(Editii_300!$B$2:$B$301,A80,Editii_300!$X$2:$X$301,1) -> 0 | T80: =IF(S80=3,1,0) -> 0
A81: DB-080 | B81: MYTHICA | C81: Saga Celor Zece Coroane | D81: 10 | E81: The Crown of Destiny | F81: Nou | G81: EN | H81: Concept propus; nescris | I81: 75000 | J81: 46325 | K81: 46350 | L81: 46352 | M81: 46354 | N81: LOT E | O81: De contractat / desemnat | P81: Fantasy epic | Q81: Titlu din plan; încheiere completă a arcului celor zece coroane. | S81: =COUNTIFS(Editii_300!$B$2:$B$301,A81,Editii_300!$X$2:$X$301,1) -> 0 | T81: =IF(S81=3,1,0) -> 0
A82: DB-081 | B82: MYTHICA | C82: The Thorn Covenant | D82: 1 | E82: The Thorn Cartographer | F82: Nou | G82: EN | H82: Concept propus; nescris | I82: 65000 | J82: 46325 | K82: 46343 | L82: 46345 | M82: 46347 | N82: LOT D | O82: De contractat / desemnat | P82: Romantasy pentru adulți | Q82: O cartografă poate șterge hotare doar renunțând la o amintire. | S82: =COUNTIFS(Editii_300!$B$2:$B$301,A82,Editii_300!$X$2:$X$301,1) -> 0 | T82: =IF(S82=3,1,0) -> 0
A83: DB-082 | B83: MYTHICA | C83: The Thorn Covenant | D83: 2 | E83: The Glasswood Pact | F83: Nou | G83: EN | H83: Concept propus; nescris | I83: 65000 | J83: 46325 | K83: 46343 | L83: 46345 | M83: 46347 | N83: LOT D | O83: De contractat / desemnat | P83: Romantasy pentru adulți | Q83: O alianță romantică este testată de un tratat care schimbă memoria. | S83: =COUNTIFS(Editii_300!$B$2:$B$301,A83,Editii_300!$X$2:$X$301,1) -> 0 | T83: =IF(S83=3,1,0) -> 0
A84: DB-083 | B84: MYTHICA | C84: The Thorn Covenant | D84: 3 | E84: The Orchard of Embers | F84: Nou | G84: EN | H84: Concept propus; nescris | I84: 65000 | J84: 46325 | K84: 46343 | L84: 46345 | M84: 46347 | N84: LOT D | O84: De contractat / desemnat | P84: Romantasy pentru adulți | Q84: Protagoniștii aleg între vindecarea unei țări și promisiunea lor. | S84: =COUNTIFS(Editii_300!$B$2:$B$301,A84,Editii_300!$X$2:$X$301,1) -> 0 | T84: =IF(S84=3,1,0) -> 0
... A91: DB-090 | B91: MYTHICA | C91: Tales of the Border Realms | D91: 5 | E91: The Dragon Who Kept the Bridge | F91: Nou | G91: EN | H91: Concept propus; nescris | I91: 40000 | J91: 46311 | K91: 46329 | L91: 46331 | M91: 46333 | N91: LOT B | O91: De contractat / desemnat | P91: Fantasy scurt independent | Q91: Un paznic și un dragon negociază pacea printr-un caz concret. | S91: =COUNTIFS(Editii_300!$B$2:$B$301,A91,Editii_300!$X$2:$X$301,1) -> 0 | T91: =IF(S91=3,1,0) -> 0
A92: DB-091 | B92: AURORA | C92: Ciclul Aurora | D92: 1 | E92: The First Light | F92: Fond | G92: EN | H92: Manuscris candidat — nevalidat editorial | I92: 90000 | J92: 46305 | K92: 46315 | L92: 46317 | M92: 46319 | N92: FOND EXISTENT | O92: De contractat / desemnat | P92: Ficțiune YA / coming-of-age | Q92: Maya Carter; responsabilitate după un incident digital, arc de zece ani. | R92: V2 circa 193,8k brute; reducere țintită propusă; metanote de proces în text. | S92: =COUNTIFS(Editii_300!$B$2:$B$301,A92,Editii_300!$X$2:$X$301,1) -> 0 | T92: =IF(S92=3,1,0) -> 0
A93: DB-092 | B93: AURORA | C93: Ciclul Aurora | D93: 2 | E93: We Meet at Sunrise | F93: Fond | G93: EN | H93: Manuscris candidat — nevalidat editorial | I93: 75000 | J93: 46305 | K93: 46315 | L93: 46317 | M93: 46319 | N93: FOND EXISTENT | O93: De contractat / desemnat | P93: Ficțiune YA / coming-of-age | Q93: Sarah; prietenie, alergare și reconstrucție personală. | R93: V1 circa 33,7k, V2 circa 86,5k; schimbare majoră, de ales master după lectură comparată. | S93: =COUNTIFS(Editii_300!$B$2:$B$301,A93,Editii_300!$X$2:$X$301,1) -> 0 | T93: =IF(S93=3,1,0) -> 0
A94: DB-093 | B94: AURORA | C94: Ciclul Aurora | D94: 3 | E94: The Atlas of Tomorrow | F94: Fond | G94: EN | H94: Manuscris candidat — nevalidat editorial | I94: 30000 | J94: 46305 | K94: 46315 | L94: 46317 | M94: 46319 | N94: FOND EXISTENT | O94: De contractat / desemnat | P94: Ficțiune YA / coming-of-age | Q94: În interior: CV for a Dreamer; Lucas și anxietatea carierei. | R94: Circa 13k, 15 capitole; interior CV for a Dreamer; nu este roman lung. | S94: =COUNTIFS(Editii_300!$B$2:$B$301,A94,Editii_300!$X$2:$X$301,1) -> 0 | T94: =IF(S94=3,1,0) -> 0
A95: DB-094 | B95: AURORA | C95: Ciclul Aurora | D95: 4 | E95: Between Two Addresses | F95: Fond | G95: EN | H95: Manuscris candidat — nevalidat editorial | I95: 28000 | J95: 46298 | K95: 46301 | L95: 46303 | M95: 46305 | N95: PILOT | O95: De contractat / desemnat | P95: Ficțiune YA / coming-of-age | Q95: Mara Anderson; locuire, comunitate și speranță. | R95: Text scurt; placeholder-uri în sursă; interiorul de publicare trebuie comparat. | S95: =COUNTIFS(Editii_300!$B$2:$B$301,A95,Editii_300!$X$2:$X$301,1) -> 0 | T95: =IF(S95=3,1,0) -> 0
A96: DB-095 | B96: AURORA | C96: Ciclul Aurora | D96: 5 | E96: Dawn of Courage | F96: Fond | G96: EN | H96: Manuscris candidat — nevalidat editorial | I96: 36000 | J96: 46305 | K96: 46315 | L96: 46317 | M96: 46319 | N96: FOND EXISTENT | O96: De contractat / desemnat | P96: Ficțiune YA / coming-of-age | Q96: Aurora Bay; curaj și relații personale. | R96: Sursa indică Volume 1 deși este Book 5 în catalog; metanote AI. | S96: =COUNTIFS(Editii_300!$B$2:$B$301,A96,Editii_300!$X$2:$X$301,1) -> 0 | T96: =IF(S96=3,1,0) -> 0
A97: DB-096 | B97: AURORA | C97: Ciclul Aurora | D97: 6 | E97: Aurora Verde | F97: Fond | G97: EN | H97: Manuscris candidat — nevalidat editorial | I97: 30000 | J97: 46305 | K97: 46315 | L97: 46317 | M97: 46319 | N97: FOND EXISTENT | O97: De contractat / desemnat | P97: Ficțiune YA / coming-of-age | Q97: Proiect comunitar, spațiu urban și implicare. | R97: Autorul din interior diferă de propunerea comercială; de separat anexele. | S97: =COUNTIFS(Editii_300!$B$2:$B$301,A97,Editii_300!$X$2:$X$301,1) -> 0 | T97: =IF(S97=3,1,0) -> 0
A98: DB-097 | B98: AURORA | C98: Ciclul Aurora | D98: 7 | E98: We, After the Feed | F98: Fond | G98: EN | H98: Manuscris candidat — nevalidat editorial | I98: 25000 | J98: 46305 | K98: 46315 | L98: 46317 | M98: 46319 | N98: FOND EXISTENT | O98: De contractat / desemnat | P98: Ficțiune YA / coming-of-age | Q98: Mara Collins; viața dincolo de validarea digitală. | R98: Juliette Moreau în sursă versus Ava Peterson & Blake Jacobs pe site; pseudonim de validat. | S98: =COUNTIFS(Editii_300!$B$2:$B$301,A98,Editii_300!$X$2:$X$301,1) -> 0 | T98: =IF(S98=3,1,0) -> 0
A99: DB-098 | B99: AURORA | C99: Ciclul Aurora | D99: 8 | E99: Aurora Admit | F99: Fond | G99: EN | H99: Manuscris candidat — nevalidat editorial | I99: 30000 | J99: 46305 | K99: 46315 | L99: 46317 | M99: 46319 | N99: FOND EXISTENT | O99: De contractat / desemnat | P99: Ficțiune YA / coming-of-age | Q99: Acces la studii, costuri și alegeri de viitor. | R99: Fișierul include instrucțiuni pentru design și placeholder art director. | S99: =COUNTIFS(Editii_300!$B$2:$B$301,A99,Editii_300!$X$2:$X$301,1) -> 0 | T99: =IF(S99=3,1,0) -> 0
A100: DB-099 | B100: AURORA | C100: Ciclul Aurora | D100: 9 | E100: Aurora Signal | F100: Fond | G100: EN | H100: Incomplet — de scris cap.7–20 | I100: 45000 | J100: 46305 | K100: 46315 | L100: 46317 | M100: 46319 | N100: FOND EXISTENT | O100: De contractat / desemnat | P100: Ficțiune YA / coming-of-age | Q100: Jade Miller; deepfake și adevăr; capitolele 7–20 sunt sinopsis. | R100: 36,3k brute includ plan/anexe; numai cap.1–6 proză, interior separat circa 21,8k. | S100: =COUNTIFS(Editii_300!$B$2:$B$301,A100,Editii_300!$X$2:$X$301,1) -> 0 | T100: =IF(S100=3,1,0) -> 0
A101: DB-100 | B101: AURORA | C101: Ciclul Aurora | D101: 10 | E101: Aurora Compass | F101: Fond | G101: EN | H101: Manuscris candidat — nevalidat editorial | I101: 30000 | J101: 46305 | K101: 46315 | L101: 46317 | M101: 46319 | N101: FOND EXISTENT | O101: De contractat / desemnat | P101: Ficțiune YA / coming-of-age | Q101: Mia Okafor; Londra, patrimoniu, implicare și sens. | R101: Autor generic în sursă versus pseudonim comercial; metanote REVISED. | S101: =COUNTIFS(Editii_300!$B$2:$B$301,A101,Editii_300!$X$2:$X$301,1) -> 0 | T101: =IF(S101=3,1,0) -> 0

Sheet Audit_17
A1: WorkID | B1: Colecție | C1: Saga | D1: Titlu | E1: Limbă sursă | F1: Versiuni | G1: Cuvinte brute | H1: Țintă editată | I1: Stare de audit | J1: Corecția necesară | K1: Master candidat — cale | L1: SHA256 sursă | M1: Publicare dovedită
A2: DB-001 | B2: NOIR | C2: Cronicile Transilvaniei | D2: Umbra Trandafirului Negru | E2: RO | F2: V1–V5 | G2: 61721 | H2: 60000 | I2: Manuscris candidat — nevalidat editorial | J2: Materiale de lucru și profiluri înaintea romanului; cronologie de corelat cu site-ul. | K2: D:\00. Downloads\Dracula Book\NOIR SERIES\Umbra Trandafirului Negru Devin.ai\Versiunea 5\MANUSCRIS_COMPLET V5.docx | L2: 0175226a7f5f95264bfe9525582c33ac2acc9e13a6cbf9cb513ab2a57a5ab7d7 | M2: Nu în materialele verificate
A3: DB-002 | B3: NOIR | C3: Cronicile Transilvaniei | D3: Marienburg: Sigiliul Fecioarei | E3: RO | F3: V1–V5 | G3: 76842 | H3: 70000 | I3: Manuscris candidat — nevalidat editorial | J3: Circa 76,8k cuvinte brute, nu 85–95k confirmate; marcaje și epoci de verificat. | K3: D:\00. Downloads\Dracula Book\NOIR SERIES\Marienburg Sigiliul Fecioarei\Versiunea 5\MARIENBURG-SIGILIUL-FECIOAREI-Draft5-Clean.docx | L3: 84ecf1904fb16685c682131c7e526a27dab96526401908da60d4d36f4186ba80 | M3: Nu în materialele verificate
A4: DB-003 | B4: NOIR | C4: Cronicile Transilvaniei | D4: Sânge și Sare la Schäßburg | E4: RO | F4: V1 | G4: 95457 | H4: 80000 | I4: Manuscris candidat — nevalidat editorial | J4: Titlul interior diferă de copertă/site; prefată de proces AI și note de eliminat. | K4: D:\00. Downloads\Dracula Book\NOIR SERIES\Sânge și Sare la Schäßburg\Versiunea 1\CIVITAS_SEX_LEGAMANTUL_DE_SARE.docx | L4: 46bba731100a53b08d5e358a8387aac78213609412b57560206734b8301b2137 | M4: Nu în materialele verificate
A5: DB-036 | B5: AMORIS | C5: Alex Damian | D5: Beneath the Skin of the Sea | E5: EN | F5: V1 | G5: 80329 | H5: 80000 | I5: Manuscris candidat — nevalidat editorial | J5: Raportul intern de 9,87/10 nu dovedește recenzie independentă sau publicare. | K5: D:\00. Downloads\Dracula Book\AMORIS SERIES\BENEATH THE SKIN OF THE SEA\Versiunea 1\BENEATH_THE_SKIN_OF_THE_SEA_Complete_Novel.docx | L5: 4ebf04663fb5ee0ac9c0aa0ef26bd2d8c8222d95db93d16cbb372b7f8e7bf44c | M5: Nu în materialele verificate
A6: DB-037 | B6: AMORIS | C6: Alex Damian | D6: Shadows in the Port | E6: EN | F6: V1 | G6: 109258 | H6: 90000 | I6: Manuscris candidat — nevalidat editorial | J6: Alex/Elena și început apropiat de Beneath; verificare sequel vs rescriere; heading 5 neidentificat. | K6: D:\00. Downloads\Dracula Book\AMORIS SERIES\Shadows in the Port\Versiunea 1\Shadows in the Port V1.docx | L6: 3f5fc3d81f584d23e7d029e90ebe2d40f7b25c5a24dfa78a81f0c2ff58e11b47 | M6: Nu în materialele verificate
A7: DB-046 | B7: AMORIS | C7: Isabella Morgan / Rue des Âmes | D7: Hotelul din Rue des Âmes | E7: EN | F7: V2 validă | G7: 96056 | H7: 85000 | I7: Manuscris candidat — nevalidat editorial | J7: Folderul V1 conține copie identică a Aurora 1; heading CHAPTER 11 neidentificat; nu se deduce automat lipsa prozei. | K7: D:\00. Downloads\Dracula Book\AMORIS SERIES\Hotelul din Rue des Âmes\Versiunea 2\Hotelul_din_Rue_des_Ames_FINAL_v2.docx | L7: a9940d5776380cb40b105429f6976219440f3ea74fb8ebc1d1b4481e9da068c3 | M7: Nu în materialele verificate
A8: DB-071 | B8: MYTHICA | C8: Saga Celor Zece Coroane | D8: The Northern Crown | E8: EN | F8: V1–V3 | G8: 106845 | H8: 95000 | I8: Manuscris candidat — nevalidat editorial | J8: Finalul anunță The Eastern Sands; planul arhivat numește vol.2 The Crown of Waters. | K8: D:\00. Downloads\Dracula Book\MYTHICA SERIES\Saga Celor Zece Coroane\Cartea 1 The_Northern_Crown\Versiunea 3\Book-1-The-Northern-Crown-EDITED-FINAL.docx | L8: c77846fdc094d5800735ab8bdc7a1a3f62248a313f5cf2ae6e757e8baef22039 | M8: Nu în materialele verificate
A9: DB-091 | B9: AURORA | C9: Ciclul Aurora | D9: The First Light | E9: EN | F9: V1–V2 | G9: 193758 | H9: 90000 | I9: Manuscris candidat — nevalidat editorial | J9: V2 circa 193,8k brute; reducere țintită propusă; metanote de proces în text. | K9: D:\00. Downloads\Dracula Book\DRACULA AURORA\Book 1\Versiunea 2\AURORA_Book1_DEVIN_FINAL.docx | L9: d187e77694194bec8887f6f7b816b27fe1938496ccf6307823205a0eb2f16eb7 | M9: Nu în materialele verificate
A10: DB-092 | B10: AURORA | C10: Ciclul Aurora | D10: We Meet at Sunrise | E10: EN | F10: V1–V2 | G10: 86474 | H10: 75000 | I10: Manuscris candidat — nevalidat editorial | J10: V1 circa 33,7k, V2 circa 86,5k; schimbare majoră, de ales master după lectură comparată. | K10: D:\00. Downloads\Dracula Book\DRACULA AURORA\Book 2\Versiunea 2\we_meet_at_sunrise_FINAL_LOCAL_LLM.docx | L10: 8211280c2445d6096b700239b9a7391c943f22c47669b159a674b257f34cc85d | M10: Nu în materialele verificate
A11: DB-093 | B11: AURORA | C11: Ciclul Aurora | D11: The Atlas of Tomorrow | E11: EN | F11: V1 | G11: 12994 | H11: 30000 | I11: Manuscris candidat — nevalidat editorial | J11: Circa 13k, 15 capitole; interior CV for a Dreamer; nu este roman lung. | K11: D:\00. Downloads\Dracula Book\DRACULA AURORA\Book 3\Versiunea 1\Aurora Book3 The Atlas of Tomorrow.docx | L11: d317c19d9fb4fe329d30e7a41e76baa9f92b5d3ce814b24d02cee07f19c80c58 | M11: Nu în materialele verificate
A12: DB-094 | B12: AURORA | C12: Ciclul Aurora | D12: Between Two Addresses | E12: EN | F12: V1 + interior | G12: 25702 | H12: 28000 | I12: Manuscris candidat — nevalidat editorial | J12: Text scurt; placeholder-uri în sursă; interiorul de publicare trebuie comparat. | K12: D:\00. Downloads\Dracula Book\DRACULA AURORA\Book 4\Versiunea 1\BetweenTwoAddresses_Complete.docx | L12: 407b05543d4c56093cd4bbc917cde2d4156c2052dbd8b4fd9960de7259e2627a | M12: Nu în materialele verificate
A13: DB-095 | B13: AURORA | C13: Ciclul Aurora | D13: Dawn of Courage | E13: EN | F13: V1 + interior | G13: 36148 | H13: 36000 | I13: Manuscris candidat — nevalidat editorial | J13: Sursa indică Volume 1 deși este Book 5 în catalog; metanote AI. | K13: D:\00. Downloads\Dracula Book\DRACULA AURORA\Book 5\Versiunea 1\DAWN_OF_COURAGE_COMPLETE_20251014_110553.docx | L13: 77f284875201cfa8867353b78fe6ac4eec7c3e23b7220fed384228705f0136a9 | M13: Nu în materialele verificate
... A18: DB-100 | B18: AURORA | C18: Ciclul Aurora | D18: Aurora Compass | E18: EN | F18: V1 + interior | G18: 27748 | H18: 30000 | I18: Manuscris candidat — nevalidat editorial | J18: Autor generic în sursă versus pseudonim comercial; metanote REVISED. | K18: D:\00. Downloads\Dracula Book\DRACULA AURORA\Book 10\Versiunea 1\Aurora_Compass_Complete_Novel.docx | L18: 1880b16da36e2a3297f526b15b2fd582963c592eb9d2595a5c3cc620e4c6e428 | M18: Nu în materialele verificate

Sheet Saga_12
A1: Colecție | B1: Saga | C1: Fond candidat | D1: Noi | E1: Total titluri | F1: Total ediții | G1: Cuvinte master
A2: NOIR | B2: Cronicile Transilvaniei | C2: 3 | D2: 7 | E2: 10 | F2: 30 | G2: 630000
A3: NOIR | B3: Carpathian Cold Cases | C3: 0 | D3: 10 | E3: 10 | F3: 30 | G3: 550000
A4: NOIR | B4: The Black Archive | C4: 0 | D4: 10 | E4: 10 | F4: 30 | G4: 350000
A5: NOIR | B5: The Borderland Files | C5: 0 | D5: 5 | E5: 5 | F5: 15 | G5: 175000
A6: AMORIS | B6: Alex Damian | C6: 2 | D6: 8 | E6: 10 | F6: 30 | G6: 650000
A7: AMORIS | B7: Isabella Morgan / Rue des Âmes | C7: 1 | D7: 9 | E7: 10 | F7: 30 | G7: 625000
A8: AMORIS | B8: Aegean Second Chances | C8: 0 | D8: 10 | E8: 10 | F8: 30 | G8: 550000
A9: AMORIS | B9: Midnight Letters | C9: 0 | D9: 5 | E9: 5 | F9: 15 | G9: 175000
A10: MYTHICA | B10: Saga Celor Zece Coroane | C10: 1 | D10: 9 | E10: 10 | F10: 30 | G10: 770000
A11: MYTHICA | B11: The Thorn Covenant | C11: 0 | D11: 5 | E11: 5 | F11: 15 | G11: 325000
A12: MYTHICA | B12: Tales of the Border Realms | C12: 0 | D12: 5 | E12: 5 | F12: 15 | G12: 200000
A13: AURORA | B13: Ciclul Aurora | C13: 10 | D13: 0 | E13: 10 | F13: 30 | G13: 419000

Sheet Editii_300
A1: EditionID | B1: WorkID | C1: Colecție | D1: Saga | E1: Volum | F1: Titlu de lucru | G1: Limbă ediție | H1: Limbă sursă | I1: Operațiune | J1: Stare | K1: Responsabil | L1: Cuvinte sursă țintă | M1: Master blocat țintă | N1: Traduceri țintă | O1: QA țintă | P1: Publicare țintă | Q1: Aprobator editorial | R1: Data publicării reale | S1: URL dovadă acces/livrare | T1: ISBN / ID extern, dacă e cazul | U1: Checksum master final | V1: Drepturi | W1: Observații | X1: Publicare verificată
A2: DB-001-EN | B2: DB-001 | C2: NOIR | D2: Cronicile Transilvaniei | E2: 1 | F2: Umbra Trandafirului Negru | G2: EN | H2: RO | I2: Traducere RO→EN | J2: Planificat | K2: De desemnat | L2: =Catalog_100!I2 -> 60000 | M2: =Catalog_100!J2 -> 46298 | N2: =Catalog_100!K2 -> 46301 | O2: =Catalog_100!L2 -> 46303 | P2: =Catalog_100!M2 -> 46305 | V2: Neconfirmat | W2: Fără ediție finală confirmată | X2: =IF(AND(J2="Publicat",Q2<>"",ISNUMBER(R2),S2<>"",U2<>"",V2="Confirmat"),1,0) -> 0
A3: DB-001-RO | B3: DB-001 | C3: NOIR | D3: Cronicile Transilvaniei | E3: 1 | F3: Umbra Trandafirului Negru | G3: RO | H3: RO | I3: Editare fond | J3: Manuscris existent | K3: De desemnat | L3: =Catalog_100!I2 -> 60000 | M3: =Catalog_100!J2 -> 46298 | N3: =Catalog_100!K2 -> 46301 | O3: =Catalog_100!L2 -> 46303 | P3: =Catalog_100!M2 -> 46305 | V3: Neconfirmat | W3: Materiale de lucru și profiluri înaintea romanului; cronologie de corelat cu site-ul. | X3: =IF(AND(J3="Publicat",Q3<>"",ISNUMBER(R3),S3<>"",U3<>"",V3="Confirmat"),1,0) -> 0
A4: DB-001-DE | B4: DB-001 | C4: NOIR | D4: Cronicile Transilvaniei | E4: 1 | F4: Umbra Trandafirului Negru | G4: DE | H4: RO | I4: Traducere RO→DE | J4: Planificat | K4: De desemnat | L4: =Catalog_100!I2 -> 60000 | M4: =Catalog_100!J2 -> 46298 | N4: =Catalog_100!K2 -> 46301 | O4: =Catalog_100!L2 -> 46303 | P4: =Catalog_100!M2 -> 46305 | V4: Neconfirmat | W4: Fără ediție finală confirmată | X4: =IF(AND(J4="Publicat",Q4<>"",ISNUMBER(R4),S4<>"",U4<>"",V4="Confirmat"),1,0) -> 0
A5: DB-002-EN | B5: DB-002 | C5: NOIR | D5: Cronicile Transilvaniei | E5: 2 | F5: Marienburg: Sigiliul Fecioarei | G5: EN | H5: RO | I5: Traducere RO→EN | J5: Planificat | K5: De desemnat | L5: =Catalog_100!I3 -> 70000 | M5: =Catalog_100!J3 -> 46305 | N5: =Catalog_100!K3 -> 46315 | O5: =Catalog_100!L3 -> 46317 | P5: =Catalog_100!M3 -> 46319 | V5: Neconfirmat | W5: Fără ediție finală confirmată | X5: =IF(AND(J5="Publicat",Q5<>"",ISNUMBER(R5),S5<>"",U5<>"",V5="Confirmat"),1,0) -> 0
A6: DB-002-RO | B6: DB-002 | C6: NOIR | D6: Cronicile Transilvaniei | E6: 2 | F6: Marienburg: Sigiliul Fecioarei | G6: RO | H6: RO | I6: Editare fond | J6: Manuscris existent | K6: De desemnat | L6: =Catalog_100!I3 -> 70000 | M6: =Catalog_100!J3 -> 46305 | N6: =Catalog_100!K3 -> 46315 | O6: =Catalog_100!L3 -> 46317 | P6: =Catalog_100!M3 -> 46319 | V6: Neconfirmat | W6: Circa 76,8k cuvinte brute, nu 85–95k confirmate; marcaje și epoci de verificat. | X6: =IF(AND(J6="Publicat",Q6<>"",ISNUMBER(R6),S6<>"",U6<>"",V6="Confirmat"),1,0) -> 0
A7: DB-002-DE | B7: DB-002 | C7: NOIR | D7: Cronicile Transilvaniei | E7: 2 | F7: Marienburg: Sigiliul Fecioarei | G7: DE | H7: RO | I7: Traducere RO→DE | J7: Planificat | K7: De desemnat | L7: =Catalog_100!I3 -> 70000 | M7: =Catalog_100!J3 -> 46305 | N7: =Catalog_100!K3 -> 46315 | O7: =Catalog_100!L3 -> 46317 | P7: =Catalog_100!M3 -> 46319 | V7: Neconfirmat | W7: Fără ediție finală confirmată | X7: =IF(AND(J7="Publicat",Q7<>"",ISNUMBER(R7),S7<>"",U7<>"",V7="Confirmat"),1,0) -> 0
A8: DB-003-EN | B8: DB-003 | C8: NOIR | D8: Cronicile Transilvaniei | E8: 3 | F8: Sânge și Sare la Schäßburg | G8: EN | H8: RO | I8: Traducere RO→EN | J8: Planificat | K8: De desemnat | L8: =Catalog_100!I4 -> 80000 | M8: =Catalog_100!J4 -> 46305 | N8: =Catalog_100!K4 -> 46315 | O8: =Catalog_100!L4 -> 46317 | P8: =Catalog_100!M4 -> 46319 | V8: Neconfirmat | W8: Fără ediție finală confirmată | X8: =IF(AND(J8="Publicat",Q8<>"",ISNUMBER(R8),S8<>"",U8<>"",V8="Confirmat"),1,0) -> 0
A9: DB-003-RO | B9: DB-003 | C9: NOIR | D9: Cronicile Transilvaniei | E9: 3 | F9: Sânge și Sare la Schäßburg | G9: RO | H9: RO | I9: Editare fond | J9: Manuscris existent | K9: De desemnat | L9: =Catalog_100!I4 -> 80000 | M9: =Catalog_100!J4 -> 46305 | N9: =Catalog_100!K4 -> 46315 | O9: =Catalog_100!L4 -> 46317 | P9: =Catalog_100!M4 -> 46319 | V9: Neconfirmat | W9: Titlul interior diferă de copertă/site; prefată de proces AI și note de eliminat. | X9: =IF(AND(J9="Publicat",Q9<>"",ISNUMBER(R9),S9<>"",U9<>"",V9="Confirmat"),1,0) -> 0
A10: DB-003-DE | B10: DB-003 | C10: NOIR | D10: Cronicile Transilvaniei | E10: 3 | F10: Sânge și Sare la Schäßburg | G10: DE | H10: RO | I10: Traducere RO→DE | J10: Planificat | K10: De desemnat | L10: =Catalog_100!I4 -> 80000 | M10: =Catalog_100!J4 -> 46305 | N10: =Catalog_100!K4 -> 46315 | O10: =Catalog_100!L4 -> 46317 | P10: =Catalog_100!M4 -> 46319 | V10: Neconfirmat | W10: Fără ediție finală confirmată | X10: =IF(AND(J10="Publicat",Q10<>"",ISNUMBER(R10),S10<>"",U10<>"",V10="Confirmat"),1,0) -> 0
A11: DB-004-EN | B11: DB-004 | C11: NOIR | D11: Cronicile Transilvaniei | E11: 4 | F11: The Bellmaker of Brașov | G11: EN | H11: EN | I11: Scriere nouă | J11: Planificat | K11: De desemnat | L11: =Catalog_100!I5 -> 60000 | M11: =Catalog_100!J5 -> 46318 | N11: =Catalog_100!K5 -> 46336 | O11: =Catalog_100!L5 -> 46338 | P11: =Catalog_100!M5 -> 46340 | V11: Neconfirmat | W11: Fără ediție finală confirmată | X11: =IF(AND(J11="Publicat",Q11<>"",ISNUMBER(R11),S11<>"",U11<>"",V11="Confirmat"),1,0) -> 0
A12: DB-004-RO | B12: DB-004 | C12: NOIR | D12: Cronicile Transilvaniei | E12: 4 | F12: The Bellmaker of Brașov | G12: RO | H12: EN | I12: Traducere EN→RO | J12: Planificat | K12: De desemnat | L12: =Catalog_100!I5 -> 60000 | M12: =Catalog_100!J5 -> 46318 | N12: =Catalog_100!K5 -> 46336 | O12: =Catalog_100!L5 -> 46338 | P12: =Catalog_100!M5 -> 46340 | V12: Neconfirmat | W12: Fără ediție finală confirmată | X12: =IF(AND(J12="Publicat",Q12<>"",ISNUMBER(R12),S12<>"",U12<>"",V12="Confirmat"),1,0) -> 0
A13: DB-004-DE | B13: DB-004 | C13: NOIR | D13: Cronicile Transilvaniei | E13: 4 | F13: The Bellmaker of Brașov | G13: DE | H13: EN | I13: Traducere EN→DE | J13: Planificat | K13: De desemnat | L13: =Catalog_100!I5 -> 60000 | M13: =Catalog_100!J5 -> 46318 | N13: =Catalog_100!K5 -> 46336 | O13: =Catalog_100!L5 -> 46338 | P13: =Catalog_100!M5 -> 46340 | V13: Neconfirmat | W13: Fără ediție finală confirmată | X13: =IF(AND(J13="Publicat",Q13<>"",ISNUMBER(R13),S13<>"",U13<>"",V13="Confirmat"),1,0) -> 0
A14: DB-005-EN | B14: DB-005 | C14: NOIR | D14: Cronicile Transilvaniei | E14: 5 | F14: The Sibiu Testament | G14: EN | H14: EN | I14: Scriere nouă | J14: Planificat | K14: De desemnat | L14: =Catalog_100!I6 -> 60000 | M14: =Catalog_100!J6 -> 46318 | N14: =Catalog_100!K6 -> 46336 | O14: =Catalog_100!L6 -> 46338 | P14: =Catalog_100!M6 -> 46340 | V14: Neconfirmat | W14: Fără ediție finală confirmată | X14: =IF(AND(J14="Publicat",Q14<>"",ISNUMBER(R14),S14<>"",U14<>"",V14="Confirmat"),1,0) -> 0
A15: DB-005-RO | B15: DB-005 | C15: NOIR | D15: Cronicile Transilvaniei | E15: 5 | F15: The Sibiu Testament | G15: RO | H15: EN | I15: Traducere EN→RO | J15: Planificat | K15: De desemnat | L15: =Catalog_100!I6 -> 60000 | M15: =Catalog_100!J6 -> 46318 | N15: =Catalog_100!K6 -> 46336 | O15: =Catalog_100!L6 -> 46338 | P15: =Catalog_100!M6 -> 46340 | V15: Neconfirmat | W15: Fără ediție finală confirmată | X15: =IF(AND(J15="Publicat",Q15<>"",ISNUMBER(R15),S15<>"",U15<>"",V15="Confirmat"),1,0) -> 0
A16: DB-005-DE | B16: DB-005 | C16: NOIR | D16: Cronicile Transilvaniei | E16: 5 | F16: The Sibiu Testament | G16: DE | H16: EN | I16: Traducere EN→DE | J16: Planificat | K16: De desemnat | L16: =Catalog_100!I6 -> 60000 | M16: =Catalog_100!J6 -> 46318 | N16: =Catalog_100!K6 -> 46336 | O16: =Catalog_100!L6 -> 46338 | P16: =Catalog_100!M6 -> 46340 | V16: Neconfirmat | W16: Fără ediție finală confirmată | X16: =IF(AND(J16="Publicat",Q16<>"",ISNUMBER(R16),S16<>"",U16<>"",V16="Confirmat"),1,0) -> 0
A17: DB-006-EN | B17: DB-006 | C17: NOIR | D17: Cronicile Transilvaniei | E17: 6 | F17: The Bistrița Bride | G17: EN | H17: EN | I17: Scriere nouă | J17: Planificat | K17: De desemnat | L17: =Catalog_100!I7 -> 60000 | M17: =Catalog_100!J7 -> 46318 | N17: =Catalog_100!K7 -> 46336 | O17: =Catalog_100!L7 -> 46338 | P17: =Catalog_100!M7 -> 46340 | V17: Neconfirmat | W17: Fără ediție finală confirmată | X17: =IF(AND(J17="Publicat",Q17<>"",ISNUMBER(R17),S17<>"",U17<>"",V17="Confirmat"),1,0) -> 0
A18: DB-006-RO | B18: DB-006 | C18: NOIR | D18: Cronicile Transilvaniei | E18: 6 | F18: The Bistrița Bride | G18: RO | H18: EN | I18: Traducere EN→RO | J18: Planificat | K18: De desemnat | L18: =Catalog_100!I7 -> 60000 | M18: =Catalog_100!J7 -> 46318 | N18: =Catalog_100!K7 -> 46336 | O18: =Catalog_100!L7 -> 46338 | P18: =Catalog_100!M7 -> 46340 | V18: Neconfirmat | W18: Fără ediție finală confirmată | X18: =IF(AND(J18="Publicat",Q18<>"",ISNUMBER(R18),S18<>"",U18<>"",V18="Confirmat"),1,0) -> 0
A19: DB-006-DE | B19: DB-006 | C19: NOIR | D19: Cronicile Transilvaniei | E19: 6 | F19: The Bistrița Bride | G19: DE | H19: EN | I19: Traducere EN→DE | J19: Planificat | K19: De desemnat | L19: =Catalog_100!I7 -> 60000 | M19: =Catalog_100!J7 -> 46318 | N19: =Catalog_100!K7 -> 46336 | O19: =Catalog_100!L7 -> 46338 | P19: =Catalog_100!M7 -> 46340 | V19: Neconfirmat | W19: Fără ediție finală confirmată | X19: =IF(AND(J19="Publicat",Q19<>"",ISNUMBER(R19),S19<>"",U19<>"",V19="Confirmat"),1,0) -> 0
A20: DB-007-EN | B20: DB-007 | C20: NOIR | D20: Cronicile Transilvaniei | E20: 7 | F20: The Locksmith of Sighișoara | G20: EN | H20: EN | I20: Scriere nouă | J20: Planificat | K20: De desemnat | L20: =Catalog_100!I8 -> 60000 | M20: =Catalog_100!J8 -> 46318 | N20: =Catalog_100!K8 -> 46336 | O20: =Catalog_100!L8 -> 46338 | P20: =Catalog_100!M8 -> 46340 | V20: Neconfirmat | W20: Fără ediție finală confirmată | X20: =IF(AND(J20="Publicat",Q20<>"",ISNUMBER(R20),S20<>"",U20<>"",V20="Confirmat"),1,0) -> 0
A21: DB-007-RO | B21: DB-007 | C21: NOIR | D21: Cronicile Transilvaniei | E21: 7 | F21: The Locksmith of Sighișoara | G21: RO | H21: EN | I21: Traducere EN→RO | J21: Planificat | K21: De desemnat | L21: =Catalog_100!I8 -> 60000 | M21: =Catalog_100!J8 -> 46318 | N21: =Catalog_100!K8 -> 46336 | O21: =Catalog_100!L8 -> 46338 | P21: =Catalog_100!M8 -> 46340 | V21: Neconfirmat | W21: Fără ediție finală confirmată | X21: =IF(AND(J21="Publicat",Q21<>"",ISNUMBER(R21),S21<>"",U21<>"",V21="Confirmat"),1,0) -> 0
A22: DB-007-DE | B22: DB-007 | C22: NOIR | D22: Cronicile Transilvaniei | E22: 7 | F22: The Locksmith of Sighișoara | G22: DE | H22: EN | I22: Traducere EN→DE | J22: Planificat | K22: De desemnat | L22: =Catalog_100!I8 -> 60000 | M22: =Catalog_100!J8 -> 46318 | N22: =Catalog_100!K8 -> 46336 | O22: =Catalog_100!L8 -> 46338 | P22: =Catalog_100!M8 -> 46340 | V22: Neconfirmat | W22: Fără ediție finală confirmată | X22: =IF(AND(J22="Publicat",Q22<>"",ISNUMBER(R22),S22<>"",U22<>"",V22="Confirmat"),1,0) -> 0
A23: DB-008-EN | B23: DB-008 | C23: NOIR | D23: Cronicile Transilvaniei | E23: 8 | F23: The Alba Iulia Cipher | G23: EN | H23: EN | I23: Scriere nouă | J23: Planificat | K23: De desemnat | L23: =Catalog_100!I9 -> 60000 | M23: =Catalog_100!J9 -> 46318 | N23: =Catalog_100!K9 -> 46336 | O23: =Catalog_100!L9 -> 46338 | P23: =Catalog_100!M9 -> 46340 | V23: Neconfirmat | W23: Fără ediție finală confirmată | X23: =IF(AND(J23="Publicat",Q23<>"",ISNUMBER(R23),S23<>"",U23<>"",V23="Confirmat"),1,0) -> 0
A24: DB-008-RO | B24: DB-008 | C24: NOIR | D24: Cronicile Transilvaniei | E24: 8 | F24: The Alba Iulia Cipher | G24: RO | H24: EN | I24: Traducere EN→RO | J24: Planificat | K24: De desemnat | L24: =Catalog_100!I9 -> 60000 | M24: =Catalog_100!J9 -> 46318 | N24: =Catalog_100!K9 -> 46336 | O24: =Catalog_100!L9 -> 46338 | P24: =Catalog_100!M9 -> 46340 | V24: Neconfirmat | W24: Fără ediție finală confirmată | X24: =IF(AND(J24="Publicat",Q24<>"",ISNUMBER(R24),S24<>"",U24<>"",V24="Confirmat"),1,0) -> 0
A25: DB-008-DE | B25: DB-008 | C25: NOIR | D25: Cronicile Transilvaniei | E25: 8 | F25: The Alba Iulia Cipher | G25: DE | H25: EN | I25: Traducere EN→DE | J25: Planificat | K25: De desemnat | L25: =Catalog_100!I9 -> 60000 | M25: =Catalog_100!J9 -> 46318 | N25: =Catalog_100!K9 -> 46336 | O25: =Catalog_100!L9 -> 46338 | P25: =Catalog_100!M9 -> 46340 | V25: Neconfirmat | W25: Fără ediție finală confirmată | X25: =IF(AND(J25="Publicat",Q25<>"",ISNUMBER(R25),S25<>"",U25<>"",V25="Confirmat"),1,0) -> 0
A26: DB-009-EN | B26: DB-009 | C26: NOIR | D26: Cronicile Transilvaniei | E26: 9 | F26: The Winter Court of Bran | G26: EN | H26: EN | I26: Scriere nouă | J26: Planificat | K26: De desemnat | L26: =Catalog_100!I10 -> 60000 | M26: =Catalog_100!J10 -> 46318 | N26: =Catalog_100!K10 -> 46336 | O26: =Catalog_100!L10 -> 46338 | P26: =Catalog_100!M10 -> 46340 | V26: Neconfirmat | W26: Fără ediție finală confirmată | X26: =IF(AND(J26="Publicat",Q26<>"",ISNUMBER(R26),S26<>"",U26<>"",V26="Confirmat"),1,0) -> 0
A27: DB-009-RO | B27: DB-009 | C27: NOIR | D27: Cronicile Transilvaniei | E27: 9 | F27: The Winter Court of Bran | G27: RO | H27: EN | I27: Traducere EN→RO | J27: Planificat | K27: De desemnat | L27: =Catalog_100!I10 -> 60000 | M27: =Catalog_100!J10 -> 46318 | N27: =Catalog_100!K10 -> 46336 | O27: =Catalog_100!L10 -> 46338 | P27: =Catalog_100!M10 -> 46340 | V27: Neconfirmat | W27: Fără ediție finală confirmată | X27: =IF(AND(J27="Publicat",Q27<>"",ISNUMBER(R27),S27<>"",U27<>"",V27="Confirmat"),1,0) -> 0
A28: DB-009-DE | B28: DB-009 | C28: NOIR | D28: Cronicile Transilvaniei | E28: 9 | F28: The Winter Court of Bran | G28: DE | H28: EN | I28: Traducere EN→DE | J28: Planificat | K28: De desemnat | L28: =Catalog_100!I10 -> 60000 | M28: =Catalog_100!J10 -> 46318 | N28: =Catalog_100!K10 -> 46336 | O28: =Catalog_100!L10 -> 46338 | P28: =Catalog_100!M10 -> 46340 | V28: Neconfirmat | W28: Fără ediție finală confirmată | X28: =IF(AND(J28="Publicat",Q28<>"",ISNUMBER(R28),S28<>"",U28<>"",V28="Confirmat"),1,0) -> 0
A29: DB-010-EN | B29: DB-010 | C29: NOIR | D29: Cronicile Transilvaniei | E29: 10 | F29: The Last Black Rose | G29: EN | H29: EN | I29: Scriere nouă | J29: Planificat | K29: De desemnat | L29: =Catalog_100!I11 -> 60000 | M29: =Catalog_100!J11 -> 46318 | N29: =Catalog_100!K11 -> 46336 | O29: =Catalog_100!L11 -> 46338 | P29: =Catalog_100!M11 -> 46340 | V29: Neconfirmat | W29: Fără ediție finală confirmată | X29: =IF(AND(J29="Publicat",Q29<>"",ISNUMBER(R29),S29<>"",U29<>"",V29="Confirmat"),1,0) -> 0
A30: DB-010-RO | B30: DB-010 | C30: NOIR | D30: Cronicile Transilvaniei | E30: 10 | F30: The Last Black Rose | G30: RO | H30: EN | I30: Traducere EN→RO | J30: Planificat | K30: De desemnat | L30: =Catalog_100!I11 -> 60000 | M30: =Catalog_100!J11 -> 46318 | N30: =Catalog_100!K11 -> 46336 | O30: =Catalog_100!L11 -> 46338 | P30: =Catalog_100!M11 -> 46340 | V30: Neconfirmat | W30: Fără ediție finală confirmată | X30: =IF(AND(J30="Publicat",Q30<>"",ISNUMBER(R30),S30<>"",U30<>"",V30="Confirmat"),1,0) -> 0
A31: DB-010-DE | B31: DB-010 | C31: NOIR | D31: Cronicile Transilvaniei | E31: 10 | F31: The Last Black Rose | G31: DE | H31: EN | I31: Traducere EN→DE | J31: Planificat | K31: De desemnat | L31: =Catalog_100!I11 -> 60000 | M31: =Catalog_100!J11 -> 46318 | N31: =Catalog_100!K11 -> 46336 | O31: =Catalog_100!L11 -> 46338 | P31: =Catalog_100!M11 -> 46340 | V31: Neconfirmat | W31: Fără ediție finală confirmată | X31: =IF(AND(J31="Publicat",Q31<>"",ISNUMBER(R31),S31<>"",U31<>"",V31="Confirmat"),1,0) -> 0
A32: DB-011-EN | B32: DB-011 | C32: NOIR | D32: Carpathian Cold Cases | E32: 1 | F32: The Witness Beneath the Ice | G32: EN | H32: EN | I32: Scriere nouă | J32: Planificat | K32: De desemnat | L32: =Catalog_100!I12 -> 55000 | M32: =Catalog_100!J12 -> 46311 | N32: =Catalog_100!K12 -> 46329 | O32: =Catalog_100!L12 -> 46331 | P32: =Catalog_100!M12 -> 46333 | V32: Neconfirmat | W32: Fără ediție finală confirmată | X32: =IF(AND(J32="Publicat",Q32<>"",ISNUMBER(R32),S32<>"",U32<>"",V32="Confirmat"),1,0) -> 0
A33: DB-011-RO | B33: DB-011 | C33: NOIR | D33: Carpathian Cold Cases | E33: 1 | F33: The Witness Beneath the Ice | G33: RO | H33: EN | I33: Traducere EN→RO | J33: Planificat | K33: De desemnat | L33: =Catalog_100!I12 -> 55000 | M33: =Catalog_100!J12 -> 46311 | N33: =Catalog_100!K12 -> 46329 | O33: =Catalog_100!L12 -> 46331 | P33: =Catalog_100!M12 -> 46333 | V33: Neconfirmat | W33: Fără ediție finală confirmată | X33: =IF(AND(J33="Publicat",Q33<>"",ISNUMBER(R33),S33<>"",U33<>"",V33="Confirmat"),1,0) -> 0
A34: DB-011-DE | B34: DB-011 | C34: NOIR | D34: Carpathian Cold Cases | E34: 1 | F34: The Witness Beneath the Ice | G34: DE | H34: EN | I34: Traducere EN→DE | J34: Planificat | K34: De desemnat | L34: =Catalog_100!I12 -> 55000 | M34: =Catalog_100!J12 -> 46311 | N34: =Catalog_100!K12 -> 46329 | O34: =Catalog_100!L12 -> 46331 | P34: =Catalog_100!M12 -> 46333 | V34: Neconfirmat | W34: Fără ediție finală confirmată | X34: =IF(AND(J34="Publicat",Q34<>"",ISNUMBER(R34),S34<>"",U34<>"",V34="Confirmat"),1,0) -> 0
A35: DB-012-EN | B35: DB-012 | C35: NOIR | D35: Carpathian Cold Cases | E35: 2 | F35: The Missing Carriage | G35: EN | H35: EN | I35: Scriere nouă | J35: Planificat | K35: De desemnat | L35: =Catalog_100!I13 -> 55000 | M35: =Catalog_100!J13 -> 46311 | N35: =Catalog_100!K13 -> 46329 | O35: =Catalog_100!L13 -> 46331 | P35: =Catalog_100!M13 -> 46333 | V35: Neconfirmat | W35: Fără ediție finală confirmată | X35: =IF(AND(J35="Publicat",Q35<>"",ISNUMBER(R35),S35<>"",U35<>"",V35="Confirmat"),1,0) -> 0
A36: DB-012-RO | B36: DB-012 | C36: NOIR | D36: Carpathian Cold Cases | E36: 2 | F36: The Missing Carriage | G36: RO | H36: EN | I36: Traducere EN→RO | J36: Planificat | K36: De desemnat | L36: =Catalog_100!I13 -> 55000 | M36: =Catalog_100!J13 -> 46311 | N36: =Catalog_100!K13 -> 46329 | O36: =Catalog_100!L13 -> 46331 | P36: =Catalog_100!M13 -> 46333 | V36: Neconfirmat | W36: Fără ediție finală confirmată | X36: =IF(AND(J36="Publicat",Q36<>"",ISNUMBER(R36),S36<>"",U36<>"",V36="Confirmat"),1,0) -> 0
A37: DB-012-DE | B37: DB-012 | C37: NOIR | D37: Carpathian Cold Cases | E37: 2 | F37: The Missing Carriage | G37: DE | H37: EN | I37: Traducere EN→DE | J37: Planificat | K37: De desemnat | L37: =Catalog_100!I13 -> 55000 | M37: =Catalog_100!J13 -> 46311 | N37: =Catalog_100!K13 -> 46329 | O37: =Catalog_100!L13 -> 46331 | P37: =Catalog_100!M13 -> 46333 | V37: Neconfirmat | W37: Fără ediție finală confirmată | X37: =IF(AND(J37="Publicat",Q37<>"",ISNUMBER(R37),S37<>"",U37<>"",V37="Confirmat"),1,0) -> 0
A38: DB-013-EN | B38: DB-013 | C38: NOIR | D38: Carpathian Cold Cases | E38: 3 | F38: The Village That Forgot Her | G38: EN | H38: EN | I38: Scriere nouă | J38: Planificat | K38: De desemnat | L38: =Catalog_100!I14 -> 55000 | M38: =Catalog_100!J14 -> 46311 | N38: =Catalog_100!K14 -> 46329 | O38: =Catalog_100!L14 -> 46331 | P38: =Catalog_100!M14 -> 46333 | V38: Neconfirmat | W38: Fără ediție finală confirmată | X38: =IF(AND(J38="Publicat",Q38<>"",ISNUMBER(R38),S38<>"",U38<>"",V38="Confirmat"),1,0) -> 0
A39: DB-013-RO | B39: DB-013 | C39: NOIR | D39: Carpathian Cold Cases | E39: 3 | F39: The Village That Forgot Her | G39: RO | H39: EN | I39: Traducere EN→RO | J39: Planificat | K39: De desemnat | L39: =Catalog_100!I14 -> 55000 | M39: =Catalog_100!J14 -> 46311 | N39: =Catalog_100!K14 -> 46329 | O39: =Catalog_100!L14 -> 46331 | P39: =Catalog_100!M14 -> 46333 | V39: Neconfirmat | W39: Fără ediție finală confirmată | X39: =IF(AND(J39="Publicat",Q39<>"",ISNUMBER(R39),S39<>"",U39<>"",V39="Confirmat"),1,0) -> 0
A40: DB-013-DE | B40: DB-013 | C40: NOIR | D40: Carpathian Cold Cases | E40: 3 | F40: The Village That Forgot Her | G40: DE | H40: EN | I40: Traducere EN→DE | J40: Planificat | K40: De desemnat | L40: =Catalog_100!I14 -> 55000 | M40: =Catalog_100!J14 -> 46311 | N40: =Catalog_100!K14 -> 46329 | O40: =Catalog_100!L14 -> 46331 | P40: =Catalog_100!M14 -> 46333 | V40: Neconfirmat | W40: Fără ediție finală confirmată | X40: =IF(AND(J40="Publicat",Q40<>"",ISNUMBER(R40),S40<>"",U40<>"",V40="Confirmat"),1,0) -> 0
A41: DB-014-EN | B41: DB-014 | C41: NOIR | D41: Carpathian Cold Cases | E41: 4 | F41: The Funeral Guest | G41: EN | H41: EN | I41: Scriere nouă | J41: Planificat | K41: De desemnat | L41: =Catalog_100!I15 -> 55000 | M41: =Catalog_100!J15 -> 46311 | N41: =Catalog_100!K15 -> 46329 | O41: =Catalog_100!L15 -> 46331 | P41: =Catalog_100!M15 -> 46333 | V41: Neconfirmat | W41: Fără ediție finală confirmată | X41: =IF(AND(J41="Publicat",Q41<>"",ISNUMBER(R41),S41<>"",U41<>"",V41="Confirmat"),1,0) -> 0
A42: DB-014-RO | B42: DB-014 | C42: NOIR | D42: Carpathian Cold Cases | E42: 4 | F42: The Funeral Guest | G42: RO | H42: EN | I42: Traducere EN→RO | J42: Planificat | K42: De desemnat | L42: =Catalog_100!I15 -> 55000 | M42: =Catalog_100!J15 -> 46311 | N42: =Catalog_100!K15 -> 46329 | O42: =Catalog_100!L15 -> 46331 | P42: =Catalog_100!M15 -> 46333 | V42: Neconfirmat | W42: Fără ediție finală confirmată | X42: =IF(AND(J42="Publicat",Q42<>"",ISNUMBER(R42),S42<>"",U42<>"",V42="Confirmat"),1,0) -> 0
A43: DB-014-DE | B43: DB-014 | C43: NOIR | D43: Carpathian Cold Cases | E43: 4 | F43: The Funeral Guest | G43: DE | H43: EN | I43: Traducere EN→DE | J43: Planificat | K43: De desemnat | L43: =Catalog_100!I15 -> 55000 | M43: =Catalog_100!J15 -> 46311 | N43: =Catalog_100!K15 -> 46329 | O43: =Catalog_100!L15 -> 46331 | P43: =Catalog_100!M15 -> 46333 | V43: Neconfirmat | W43: Fără ediție finală confirmată | X43: =IF(AND(J43="Publicat",Q43<>"",ISNUMBER(R43),S43<>"",U43<>"",V43="Confirmat"),1,0) -> 0
A44: DB-015-EN | B44: DB-015 | C44: NOIR | D44: Carpathian Cold Cases | E44: 5 | F44: The Quarry Silence | G44: EN | H44: EN | I44: Scriere nouă | J44: Planificat | K44: De desemnat | L44: =Catalog_100!I16 -> 55000 | M44: =Catalog_100!J16 -> 46311 | N44: =Catalog_100!K16 -> 46329 | O44: =Catalog_100!L16 -> 46331 | P44: =Catalog_100!M16 -> 46333 | V44: Neconfirmat | W44: Fără ediție finală confirmată | X44: =IF(AND(J44="Publicat",Q44<>"",ISNUMBER(R44),S44<>"",U44<>"",V44="Confirmat"),1,0) -> 0
A45: DB-015-RO | B45: DB-015 | C45: NOIR | D45: Carpathian Cold Cases | E45: 5 | F45: The Quarry Silence | G45: RO | H45: EN | I45: Traducere EN→RO | J45: Planificat | K45: De desemnat | L45: =Catalog_100!I16 -> 55000 | M45: =Catalog_100!J16 -> 46311 | N45: =Catalog_100!K16 -> 46329 | O45: =Catalog_100!L16 -> 46331 | P45: =Catalog_100!M16 -> 46333 | V45: Neconfirmat | W45: Fără ediție finală confirmată | X45: =IF(AND(J45="Publicat",Q45<>"",ISNUMBER(R45),S45<>"",U45<>"",V45="Confirmat"),1,0) -> 0
A46: DB-015-DE | B46: DB-015 | C46: NOIR | D46: Carpathian Cold Cases | E46: 5 | F46: The Quarry Silence | G46: DE | H46: EN | I46: Traducere EN→DE | J46: Planificat | K46: De desemnat | L46: =Catalog_100!I16 -> 55000 | M46: =Catalog_100!J16 -> 46311 | N46: =Catalog_100!K16 -> 46329 | O46: =Catalog_100!L16 -> 46331 | P46: =Catalog_100!M16 -> 46333 | V46: Neconfirmat | W46: Fără ediție finală confirmată | X46: =IF(AND(J46="Publicat",Q46<>"",ISNUMBER(R46),S46<>"",U46<>"",V46="Confirmat"),1,0) -> 0
A47: DB-016-EN | B47: DB-016 | C47: NOIR | D47: Carpathian Cold Cases | E47: 6 | F47: The Last Night at the Observatory | G47: EN | H47: EN | I47: Scriere nouă | J47: Planificat | K47: De desemnat | L47: =Catalog_100!I17 -> 55000 | M47: =Catalog_100!J17 -> 46311 | N47: =Catalog_100!K17 -> 46329 | O47: =Catalog_100!L17 -> 46331 | P47: =Catalog_100!M17 -> 46333 | V47: Neconfirmat | W47: Fără ediție finală confirmată | X47: =IF(AND(J47="Publicat",Q47<>"",ISNUMBER(R47),S47<>"",U47<>"",V47="Confirmat"),1,0) -> 0
A48: DB-016-RO | B48: DB-016 | C48: NOIR | D48: Carpathian Cold Cases | E48: 6 | F48: The Last Night at the Observatory | G48: RO | H48: EN | I48: Traducere EN→RO | J48: Planificat | K48: De desemnat | L48: =Catalog_100!I17 -> 55000 | M48: =Catalog_100!J17 -> 46311 | N48: =Catalog_100!K17 -> 46329 | O48: =Catalog_100!L17 -> 46331 | P48: =Catalog_100!M17 -> 46333 | V48: Neconfirmat | W48: Fără ediție finală confirmată | X48: =IF(AND(J48="Publicat",Q48<>"",ISNUMBER(R48),S48<>"",U48<>"",V48="Confirmat"),1,0) -> 0
A49: DB-016-DE | B49: DB-016 | C49: NOIR | D49: Carpathian Cold Cases | E49: 6 | F49: The Last Night at the Observatory | G49: DE | H49: EN | I49: Traducere EN→DE | J49: Planificat | K49: De desemnat | L49: =Catalog_100!I17 -> 55000 | M49: =Catalog_100!J17 -> 46311 | N49: =Catalog_100!K17 -> 46329 | O49: =Catalog_100!L17 -> 46331 | P49: =Catalog_100!M17 -> 46333 | V49: Neconfirmat | W49: Fără ediție finală confirmată | X49: =IF(AND(J49="Publicat",Q49<>"",ISNUMBER(R49),S49<>"",U49<>"",V49="Confirmat"),1,0) -> 0
A50: DB-017-EN | B50: DB-017 | C50: NOIR | D50: Carpathian Cold Cases | E50: 7 | F50: The Borrowed Identity | G50: EN | H50: EN | I50: Scriere nouă | J50: Planificat | K50: De desemnat | L50: =Catalog_100!I18 -> 55000 | M50: =Catalog_100!J18 -> 46311 | N50: =Catalog_100!K18 -> 46329 | O50: =Catalog_100!L18 -> 46331 | P50: =Catalog_100!M18 -> 46333 | V50: Neconfirmat | W50: Fără ediție finală confirmată | X50: =IF(AND(J50="Publicat",Q50<>"",ISNUMBER(R50),S50<>"",U50<>"",V50="Confirmat"),1,0) -> 0
A51: DB-017-RO | B51: DB-017 | C51: NOIR | D51: Carpathian Cold Cases | E51: 7 | F51: The Borrowed Identity | G51: RO | H51: EN | I51: Traducere EN→RO | J51: Planificat | K51: De desemnat | L51: =Catalog_100!I18 -> 55000 | M51: =Catalog_100!J18 -> 46311 | N51: =Catalog_100!K18 -> 46329 | O51: =Catalog_100!L18 -> 46331 | P51: =Catalog_100!M18 -> 46333 | V51: Neconfirmat | W51: Fără ediție finală confirmată | X51: =IF(AND(J51="Publicat",Q51<>"",ISNUMBER(R51),S51<>"",U51<>"",V51="Confirmat"),1,0) -> 0
A52: DB-017-DE | B52: DB-017 | C52: NOIR | D52: Carpathian Cold Cases | E52: 7 | F52: The Borrowed Identity | G52: DE | H52: EN | I52: Traducere EN→DE | J52: Planificat | K52: De desemnat | L52: =Catalog_100!I18 -> 55000 | M52: =Catalog_100!J18 -> 46311 | N52: =Catalog_100!K18 -> 46329 | O52: =Catalog_100!L18 -> 46331 | P52: =Catalog_100!M18 -> 46333 | V52: Neconfirmat | W52: Fără ediție finală confirmată | X52: =IF(AND(J52="Publicat",Q52<>"",ISNUMBER(R52),S52<>"",U52<>"",V52="Confirmat"),1,0) -> 0
A53: DB-018-EN | B53: DB-018 | C53: NOIR | D53: Carpathian Cold Cases | E53: 8 | F53: The Lake House Ledger | G53: EN | H53: EN | I53: Scriere nouă | J53: Planificat | K53: De desemnat | L53: =Catalog_100!I19 -> 55000 | M53: =Catalog_100!J19 -> 46311 | N53: =Catalog_100!K19 -> 46329 | O53: =Catalog_100!L19 -> 46331 | P53: =Catalog_100!M19 -> 46333 | V53: Neconfirmat | W53: Fără ediție finală confirmată | X53: =IF(AND(J53="Publicat",Q53<>"",ISNUMBER(R53),S53<>"",U53<>"",V53="Confirmat"),1,0) -> 0
A54: DB-018-RO | B54: DB-018 | C54: NOIR | D54: Carpathian Cold Cases | E54: 8 | F54: The Lake House Ledger | G54: RO | H54: EN | I54: Traducere EN→RO | J54: Planificat | K54: De desemnat | L54: =Catalog_100!I19 -> 55000 | M54: =Catalog_100!J19 -> 46311 | N54: =Catalog_100!K19 -> 46329 | O54: =Catalog_100!L19 -> 46331 | P54: =Catalog_100!M19 -> 46333 | V54: Neconfirmat | W54: Fără ediție finală confirmată | X54: =IF(AND(J54="Publicat",Q54<>"",ISNUMBER(R54),S54<>"",U54<>"",V54="Confirmat"),1,0) -> 0
A55: DB-018-DE | B55: DB-018 | C55: NOIR | D55: Carpathian Cold Cases | E55: 8 | F55: The Lake House Ledger | G55: DE | H55: EN | I55: Traducere EN→DE | J55: Planificat | K55: De desemnat | L55: =Catalog_100!I19 -> 55000 | M55: =Catalog_100!J19 -> 46311 | N55: =Catalog_100!K19 -> 46329 | O55: =Catalog_100!L19 -> 46331 | P55: =Catalog_100!M19 -> 46333 | V55: Neconfirmat | W55: Fără ediție finală confirmată | X55: =IF(AND(J55="Publicat",Q55<>"",ISNUMBER(R55),S55<>"",U55<>"",V55="Confirmat"),1,0) -> 0
A56: DB-019-EN | B56: DB-019 | C56: NOIR | D56: Carpathian Cold Cases | E56: 9 | F56: The Unsent Testimony | G56: EN | H56: EN | I56: Scriere nouă | J56: Planificat | K56: De desemnat | L56: =Catalog_100!I20 -> 55000 | M56: =Catalog_100!J20 -> 46311 | N56: =Catalog_100!K20 -> 46329 | O56: =Catalog_100!L20 -> 46331 | P56: =Catalog_100!M20 -> 46333 | V56: Neconfirmat | W56: Fără ediție finală confirmată | X56: =IF(AND(J56="Publicat",Q56<>"",ISNUMBER(R56),S56<>"",U56<>"",V56="Confirmat"),1,0) -> 0
A57: DB-019-RO | B57: DB-019 | C57: NOIR | D57: Carpathian Cold Cases | E57: 9 | F57: The Unsent Testimony | G57: RO | H57: EN | I57: Traducere EN→RO | J57: Planificat | K57: De desemnat | L57: =Catalog_100!I20 -> 55000 | M57: =Catalog_100!J20 -> 46311 | N57: =Catalog_100!K20 -> 46329 | O57: =Catalog_100!L20 -> 46331 | P57: =Catalog_100!M20 -> 46333 | V57: Neconfirmat | W57: Fără ediție finală confirmată | X57: =IF(AND(J57="Publicat",Q57<>"",ISNUMBER(R57),S57<>"",U57<>"",V57="Confirmat"),1,0) -> 0
A58: DB-019-DE | B58: DB-019 | C58: NOIR | D58: Carpathian Cold Cases | E58: 9 | F58: The Unsent Testimony | G58: DE | H58: EN | I58: Traducere EN→DE | J58: Planificat | K58: De desemnat | L58: =Catalog_100!I20 -> 55000 | M58: =Catalog_100!J20 -> 46311 | N58: =Catalog_100!K20 -> 46329 | O58: =Catalog_100!L20 -> 46331 | P58: =Catalog_100!M20 -> 46333 | V58: Neconfirmat | W58: Fără ediție finală confirmată | X58: =IF(AND(J58="Publicat",Q58<>"",ISNUMBER(R58),S58<>"",U58<>"",V58="Confirmat"),1,0) -> 0
A59: DB-020-EN | B59: DB-020 | C59: NOIR | D59: Carpathian Cold Cases | E59: 10 | F59: The Mountain Keeps the Names | G59: EN | H59: EN | I59: Scriere nouă | J59: Planificat | K59: De desemnat | L59: =Catalog_100!I21 -> 55000 | M59: =Catalog_100!J21 -> 46311 | N59: =Catalog_100!K21 -> 46329 | O59: =Catalog_100!L21 -> 46331 | P59: =Catalog_100!M21 -> 46333 | V59: Neconfirmat | W59: Fără ediție finală confirmată | X59: =IF(AND(J59="Publicat",Q59<>"",ISNUMBER(R59),S59<>"",U59<>"",V59="Confirmat"),1,0) -> 0
A60: DB-020-RO | B60: DB-020 | C60: NOIR | D60: Carpathian Cold Cases | E60: 10 | F60: The Mountain Keeps the Names | G60: RO | H60: EN | I60: Traducere EN→RO | J60: Planificat | K60: De desemnat | L60: =Catalog_100!I21 -> 55000 | M60: =Catalog_100!J21 -> 46311 | N60: =Catalog_100!K21 -> 46329 | O60: =Catalog_100!L21 -> 46331 | P60: =Catalog_100!M21 -> 46333 | V60: Neconfirmat | W60: Fără ediție finală confirmată | X60: =IF(AND(J60="Publicat",Q60<>"",ISNUMBER(R60),S60<>"",U60<>"",V60="Confirmat"),1,0) -> 0
A61: DB-020-DE | B61: DB-020 | C61: NOIR | D61: Carpathian Cold Cases | E61: 10 | F61: The Mountain Keeps the Names | G61: DE | H61: EN | I61: Traducere EN→DE | J61: Planificat | K61: De desemnat | L61: =Catalog_100!I21 -> 55000 | M61: =Catalog_100!J21 -> 46311 | N61: =Catalog_100!K21 -> 46329 | O61: =Catalog_100!L21 -> 46331 | P61: =Catalog_100!M21 -> 46333 | V61: Neconfirmat | W61: Fără ediție finală confirmată | X61: =IF(AND(J61="Publicat",Q61<>"",ISNUMBER(R61),S61<>"",U61<>"",V61="Confirmat"),1,0) -> 0
A62: DB-021-EN | B62: DB-021 | C62: NOIR | D62: The Black Archive | E62: 1 | F62: The Ink That Remembers | G62: EN | H62: EN | I62: Scriere nouă | J62: Planificat | K62: De desemnat | L62: =Catalog_100!I22 -> 35000 | M62: =Catalog_100!J22 -> 46304 | N62: =Catalog_100!K22 -> 46322 | O62: =Catalog_100!L22 -> 46324 | P62: =Catalog_100!M22 -> 46326 | V62: Neconfirmat | W62: Fără ediție finală confirmată | X62: =IF(AND(J62="Publicat",Q62<>"",ISNUMBER(R62),S62<>"",U62<>"",V62="Confirmat"),1,0) -> 0
A63: DB-021-RO | B63: DB-021 | C63: NOIR | D63: The Black Archive | E63: 1 | F63: The Ink That Remembers | G63: RO | H63: EN | I63: Traducere EN→RO | J63: Planificat | K63: De desemnat | L63: =Catalog_100!I22 -> 35000 | M63: =Catalog_100!J22 -> 46304 | N63: =Catalog_100!K22 -> 46322 | O63: =Catalog_100!L22 -> 46324 | P63: =Catalog_100!M22 -> 46326 | V63: Neconfirmat | W63: Fără ediție finală confirmată | X63: =IF(AND(J63="Publicat",Q63<>"",ISNUMBER(R63),S63<>"",U63<>"",V63="Confirmat"),1,0) -> 0
A64: DB-021-DE | B64: DB-021 | C64: NOIR | D64: The Black Archive | E64: 1 | F64: The Ink That Remembers | G64: DE | H64: EN | I64: Traducere EN→DE | J64: Planificat | K64: De desemnat | L64: =Catalog_100!I22 -> 35000 | M64: =Catalog_100!J22 -> 46304 | N64: =Catalog_100!K22 -> 46322 | O64: =Catalog_100!L22 -> 46324 | P64: =Catalog_100!M22 -> 46326 | V64: Neconfirmat | W64: Fără ediție finală confirmată | X64: =IF(AND(J64="Publicat",Q64<>"",ISNUMBER(R64),S64<>"",U64<>"",V64="Confirmat"),1,0) -> 0
A65: DB-022-EN | B65: DB-022 | C65: NOIR | D65: The Black Archive | E65: 2 | F65: The Chapel of Unkept Promises | G65: EN | H65: EN | I65: Scriere nouă | J65: Planificat | K65: De desemnat | L65: =Catalog_100!I23 -> 35000 | M65: =Catalog_100!J23 -> 46304 | N65: =Catalog_100!K23 -> 46322 | O65: =Catalog_100!L23 -> 46324 | P65: =Catalog_100!M23 -> 46326 | V65: Neconfirmat | W65: Fără ediție finală confirmată | X65: =IF(AND(J65="Publicat",Q65<>"",ISNUMBER(R65),S65<>"",U65<>"",V65="Confirmat"),1,0) -> 0
A66: DB-022-RO | B66: DB-022 | C66: NOIR | D66: The Black Archive | E66: 2 | F66: The Chapel of Unkept Promises | G66: RO | H66: EN | I66: Traducere EN→RO | J66: Planificat | K66: De desemnat | L66: =Catalog_100!I23 -> 35000 | M66: =Catalog_100!J23 -> 46304 | N66: =Catalog_100!K23 -> 46322 | O66: =Catalog_100!L23 -> 46324 | P66: =Catalog_100!M23 -> 46326 | V66: Neconfirmat | W66: Fără ediție finală confirmată | X66: =IF(AND(J66="Publicat",Q66<>"",ISNUMBER(R66),S66<>"",U66<>"",V66="Confirmat"),1,0) -> 0
A67: DB-022-DE | B67: DB-022 | C67: NOIR | D67: The Black Archive | E67: 2 | F67: The Chapel of Unkept Promises | G67: DE | H67: EN | I67: Traducere EN→DE | J67: Planificat | K67: De desemnat | L67: =Catalog_100!I23 -> 35000 | M67: =Catalog_100!J23 -> 46304 | N67: =Catalog_100!K23 -> 46322 | O67: =Catalog_100!L23 -> 46324 | P67: =Catalog_100!M23 -> 46326 | V67: Neconfirmat | W67: Fără ediție finală confirmată | X67: =IF(AND(J67="Publicat",Q67<>"",ISNUMBER(R67),S67<>"",U67<>"",V67="Confirmat"),1,0) -> 0
A68: DB-023-EN | B68: DB-023 | C68: NOIR | D68: The Black Archive | E68: 3 | F68: The Portrait Without Eyes | G68: EN | H68: EN | I68: Scriere nouă | J68: Planificat | K68: De desemnat | L68: =Catalog_100!I24 -> 35000 | M68: =Catalog_100!J24 -> 46304 | N68: =Catalog_100!K24 -> 46322 | O68: =Catalog_100!L24 -> 46324 | P68: =Catalog_100!M24 -> 46326 | V68: Neconfirmat | W68: Fără ediție finală confirmată | X68: =IF(AND(J68="Publicat",Q68<>"",ISNUMBER(R68),S68<>"",U68<>"",V68="Confirmat"),1,0) -> 0
A69: DB-023-RO | B69: DB-023 | C69: NOIR | D69: The Black Archive | E69: 3 | F69: The Portrait Without Eyes | G69: RO | H69: EN | I69: Traducere EN→RO | J69: Planificat | K69: De desemnat | L69: =Catalog_100!I24 -> 35000 | M69: =Catalog_100!J24 -> 46304 | N69: =Catalog_100!K24 -> 46322 | O69: =Catalog_100!L24 -> 46324 | P69: =Catalog_100!M24 -> 46326 | V69: Neconfirmat | W69: Fără ediție finală confirmată | X69: =IF(AND(J69="Publicat",Q69<>"",ISNUMBER(R69),S69<>"",U69<>"",V69="Confirmat"),1,0) -> 0
A70: DB-023-DE | B70: DB-023 | C70: NOIR | D70: The Black Archive | E70: 3 | F70: The Portrait Without Eyes | G70: DE | H70: EN | I70: Traducere EN→DE | J70: Planificat | K70: De desemnat | L70: =Catalog_100!I24 -> 35000 | M70: =Catalog_100!J24 -> 46304 | N70: =Catalog_100!K24 -> 46322 | O70: =Catalog_100!L24 -> 46324 | P70: =Catalog_100!M24 -> 46326 | V70: Neconfirmat | W70: Fără ediție finală confirmată | X70: =IF(AND(J70="Publicat",Q70<>"",ISNUMBER(R70),S70<>"",U70<>"",V70="Confirmat"),1,0) -> 0
A71: DB-024-EN | B71: DB-024 | C71: NOIR | D71: The Black Archive | E71: 4 | F71: The House of Borrowed Winters | G71: EN | H71: EN | I71: Scriere nouă | J71: Planificat | K71: De desemnat | L71: =Catalog_100!I25 -> 35000 | M71: =Catalog_100!J25 -> 46304 | N71: =Catalog_100!K25 -> 46322 | O71: =Catalog_100!L25 -> 46324 | P71: =Catalog_100!M25 -> 46326 | V71: Neconfirmat | W71: Fără ediție finală confirmată | X71: =IF(AND(J71="Publicat",Q71<>"",ISNUMBER(R71),S71<>"",U71<>"",V71="Confirmat"),1,0) -> 0
A72: DB-024-RO | B72: DB-024 | C72: NOIR | D72: The Black Archive | E72: 4 | F72: The House of Borrowed Winters | G72: RO | H72: EN | I72: Traducere EN→RO | J72: Planificat | K72: De desemnat | L72: =Catalog_100!I25 -> 35000 | M72: =Catalog_100!J25 -> 46304 | N72: =Catalog_100!K25 -> 46322 | O72: =Catalog_100!L25 -> 46324 | P72: =Catalog_100!M25 -> 46326 | V72: Neconfirmat | W72: Fără ediție finală confirmată | X72: =IF(AND(J72="Publicat",Q72<>"",ISNUMBER(R72),S72<>"",U72<>"",V72="Confirmat"),1,0) -> 0
A73: DB-024-DE | B73: DB-024 | C73: NOIR | D73: The Black Archive | E73: 4 | F73: The House of Borrowed Winters | G73: DE | H73: EN | I73: Traducere EN→DE | J73: Planificat | K73: De desemnat | L73: =Catalog_100!I25 -> 35000 | M73: =Catalog_100!J25 -> 46304 | N73: =Catalog_100!K25 -> 46322 | O73: =Catalog_100!L25 -> 46324 | P73: =Catalog_100!M25 -> 46326 | V73: Neconfirmat | W73: Fără ediție finală confirmată | X73: =IF(AND(J73="Publicat",Q73<>"",ISNUMBER(R73),S73<>"",U73<>"",V73="Confirmat"),1,0) -> 0
A74: DB-025-EN | B74: DB-025 | C74: NOIR | D74: The Black Archive | E74: 5 | F74: The Salt Mirror | G74: EN | H74: EN | I74: Scriere nouă | J74: Planificat | K74: De desemnat | L74: =Catalog_100!I26 -> 35000 | M74: =Catalog_100!J26 -> 46304 | N74: =Catalog_100!K26 -> 46322 | O74: =Catalog_100!L26 -> 46324 | P74: =Catalog_100!M26 -> 46326 | V74: Neconfirmat | W74: Fără ediție finală confirmată | X74: =IF(AND(J74="Publicat",Q74<>"",ISNUMBER(R74),S74<>"",U74<>"",V74="Confirmat"),1,0) -> 0
A75: DB-025-RO | B75: DB-025 | C75: NOIR | D75: The Black Archive | E75: 5 | F75: The Salt Mirror | G75: RO | H75: EN | I75: Traducere EN→RO | J75: Planificat | K75: De desemnat | L75: =Catalog_100!I26 -> 35000 | M75: =Catalog_100!J26 -> 46304 | N75: =Catalog_100!K26 -> 46322 | O75: =Catalog_100!L26 -> 46324 | P75: =Catalog_100!M26 -> 46326 | V75: Neconfirmat | W75: Fără ediție finală confirmată | X75: =IF(AND(J75="Publicat",Q75<>"",ISNUMBER(R75),S75<>"",U75<>"",V75="Confirmat"),1,0) -> 0
A76: DB-025-DE | B76: DB-025 | C76: NOIR | D76: The Black Archive | E76: 5 | F76: The Salt Mirror | G76: DE | H76: EN | I76: Traducere EN→DE | J76: Planificat | K76: De desemnat | L76: =Catalog_100!I26 -> 35000 | M76: =Catalog_100!J26 -> 46304 | N76: =Catalog_100!K26 -> 46322 | O76: =Catalog_100!L26 -> 46324 | P76: =Catalog_100!M26 -> 46326 | V76: Neconfirmat | W76: Fără ediție finală confirmată | X76: =IF(AND(J76="Publicat",Q76<>"",ISNUMBER(R76),S76<>"",U76<>"",V76="Confirmat"),1,0) -> 0
A77: DB-026-EN | B77: DB-026 | C77: NOIR | D77: The Black Archive | E77: 6 | F77: The Orchard of Silent Bells | G77: EN | H77: EN | I77: Scriere nouă | J77: Planificat | K77: De desemnat | L77: =Catalog_100!I27 -> 35000 | M77: =Catalog_100!J27 -> 46304 | N77: =Catalog_100!K27 -> 46322 | O77: =Catalog_100!L27 -> 46324 | P77: =Catalog_100!M27 -> 46326 | V77: Neconfirmat | W77: Fără ediție finală confirmată | X77: =IF(AND(J77="Publicat",Q77<>"",ISNUMBER(R77),S77<>"",U77<>"",V77="Confirmat"),1,0) -> 0
A78: DB-026-RO | B78: DB-026 | C78: NOIR | D78: The Black Archive | E78: 6 | F78: The Orchard of Silent Bells | G78: RO | H78: EN | I78: Traducere EN→RO | J78: Planificat | K78: De desemnat | L78: =Catalog_100!I27 -> 35000 | M78: =Catalog_100!J27 -> 46304 | N78: =Catalog_100!K27 -> 46322 | O78: =Catalog_100!L27 -> 46324 | P78: =Catalog_100!M27 -> 46326 | V78: Neconfirmat | W78: Fără ediție finală confirmată | X78: =IF(AND(J78="Publicat",Q78<>"",ISNUMBER(R78),S78<>"",U78<>"",V78="Confirmat"),1,0) -> 0
A79: DB-026-DE | B79: DB-026 | C79: NOIR | D79: The Black Archive | E79: 6 | F79: The Orchard of Silent Bells | G79: DE | H79: EN | I79: Traducere EN→DE | J79: Planificat | K79: De desemnat | L79: =Catalog_100!I27 -> 35000 | M79: =Catalog_100!J27 -> 46304 | N79: =Catalog_100!K27 -> 46322 | O79: =Catalog_100!L27 -> 46324 | P79: =Catalog_100!M27 -> 46326 | V79: Neconfirmat | W79: Fără ediție finală confirmată | X79: =IF(AND(J79="Publicat",Q79<>"",ISNUMBER(R79),S79<>"",U79<>"",V79="Confirmat"),1,0) -> 0
A80: DB-027-EN | B80: DB-027 | C80: NOIR | D80: The Black Archive | E80: 7 | F80: The Cartographer's Last Room | G80: EN | H80: EN | I80: Scriere nouă | J80: Planificat | K80: De desemnat | L80: =Catalog_100!I28 -> 35000 | M80: =Catalog_100!J28 -> 46304 | N80: =Catalog_100!K28 -> 46322 | O80: =Catalog_100!L28 -> 46324 | P80: =Catalog_100!M28 -> 46326 | V80: Neconfirmat | W80: Fără ediție finală confirmată | X80: =IF(AND(J80="Publicat",Q80<>"",ISNUMBER(R80),S80<>"",U80<>"",V80="Confirmat"),1,0) -> 0
A81: DB-027-RO | B81: DB-027 | C81: NOIR | D81: The Black Archive | E81: 7 | F81: The Cartographer's Last Room | G81: RO | H81: EN | I81: Traducere EN→RO | J81: Planificat | K81: De desemnat | L81: =Catalog_100!I28 -> 35000 | M81: =Catalog_100!J28 -> 46304 | N81: =Catalog_100!K28 -> 46322 | O81: =Catalog_100!L28 -> 46324 | P81: =Catalog_100!M28 -> 46326 | V81: Neconfirmat | W81: Fără ediție finală confirmată | X81: =IF(AND(J81="Publicat",Q81<>"",ISNUMBER(R81),S81<>"",U81<>"",V81="Confirmat"),1,0) -> 0
A82: DB-027-DE | B82: DB-027 | C82: NOIR | D82: The Black Archive | E82: 7 | F82: The Cartographer's Last Room | G82: DE | H82: EN | I82: Traducere EN→DE | J82: Planificat | K82: De desemnat | L82: =Catalog_100!I28 -> 35000 | M82: =Catalog_100!J28 -> 46304 | N82: =Catalog_100!K28 -> 46322 | O82: =Catalog_100!L28 -> 46324 | P82: =Catalog_100!M28 -> 46326 | V82: Neconfirmat | W82: Fără ediție finală confirmată | X82: =IF(AND(J82="Publicat",Q82<>"",ISNUMBER(R82),S82<>"",U82<>"",V82="Confirmat"),1,0) -> 0
A83: DB-028-EN | B83: DB-028 | C83: NOIR | D83: The Black Archive | E83: 8 | F83: The Seamstress of Midnight | G83: EN | H83: EN | I83: Scriere nouă | J83: Planificat | K83: De desemnat | L83: =Catalog_100!I29 -> 35000 | M83: =Catalog_100!J29 -> 46304 | N83: =Catalog_100!K29 -> 46322 | O83: =Catalog_100!L29 -> 46324 | P83: =Catalog_100!M29 -> 46326 | V83: Neconfirmat | W83: Fără ediție finală confirmată | X83: =IF(AND(J83="Publicat",Q83<>"",ISNUMBER(R83),S83<>"",U83<>"",V83="Confirmat"),1,0) -> 0
A84: DB-028-RO | B84: DB-028 | C84: NOIR | D84: The Black Archive | E84: 8 | F84: The Seamstress of Midnight | G84: RO | H84: EN | I84: Traducere EN→RO | J84: Planificat | K84: De desemnat | L84: =Catalog_100!I29 -> 35000 | M84: =Catalog_100!J29 -> 46304 | N84: =Catalog_100!K29 -> 46322 | O84: =Catalog_100!L29 -> 46324 | P84: =Catalog_100!M29 -> 46326 | V84: Neconfirmat | W84: Fără ediție finală confirmată | X84: =IF(AND(J84="Publicat",Q84<>"",ISNUMBER(R84),S84<>"",U84<>"",V84="Confirmat"),1,0) -> 0
A85: DB-028-DE | B85: DB-028 | C85: NOIR | D85: The Black Archive | E85: 8 | F85: The Seamstress of Midnight | G85: DE | H85: EN | I85: Traducere EN→DE | J85: Planificat | K85: De desemnat | L85: =Catalog_100!I29 -> 35000 | M85: =Catalog_100!J29 -> 46304 | N85: =Catalog_100!K29 -> 46322 | O85: =Catalog_100!L29 -> 46324 | P85: =Catalog_100!M29 -> 46326 | V85: Neconfirmat | W85: Fără ediție finală confirmată | X85: =IF(AND(J85="Publicat",Q85<>"",ISNUMBER(R85),S85<>"",U85<>"",V85="Confirmat"),1,0) -> 0
A86: DB-029-EN | B86: DB-029 | C86: NOIR | D86: The Black Archive | E86: 9 | F86: The Clock Beneath the Crypt | G86: EN | H86: EN | I86: Scriere nouă | J86: Planificat | K86: De desemnat | L86: =Catalog_100!I30 -> 35000 | M86: =Catalog_100!J30 -> 46304 | N86: =Catalog_100!K30 -> 46322 | O86: =Catalog_100!L30 -> 46324 | P86: =Catalog_100!M30 -> 46326 | V86: Neconfirmat | W86: Fără ediție finală confirmată | X86: =IF(AND(J86="Publicat",Q86<>"",ISNUMBER(R86),S86<>"",U86<>"",V86="Confirmat"),1,0) -> 0
A87: DB-029-RO | B87: DB-029 | C87: NOIR | D87: The Black Archive | E87: 9 | F87: The Clock Beneath the Crypt | G87: RO | H87: EN | I87: Traducere EN→RO | J87: Planificat | K87: De desemnat | L87: =Catalog_100!I30 -> 35000 | M87: =Catalog_100!J30 -> 46304 | N87: =Catalog_100!K30 -> 46322 | O87: =Catalog_100!L30 -> 46324 | P87: =Catalog_100!M30 -> 46326 | V87: Neconfirmat | W87: Fără ediție finală confirmată | X87: =IF(AND(J87="Publicat",Q87<>"",ISNUMBER(R87),S87<>"",U87<>"",V87="Confirmat"),1,0) -> 0
A88: DB-029-DE | B88: DB-029 | C88: NOIR | D88: The Black Archive | E88: 9 | F88: The Clock Beneath the Crypt | G88: DE | H88: EN | I88: Traducere EN→DE | J88: Planificat | K88: De desemnat | L88: =Catalog_100!I30 -> 35000 | M88: =Catalog_100!J30 -> 46304 | N88: =Catalog_100!K30 -> 46322 | O88: =Catalog_100!L30 -> 46324 | P88: =Catalog_100!M30 -> 46326 | V88: Neconfirmat | W88: Fără ediție finală confirmată | X88: =IF(AND(J88="Publicat",Q88<>"",ISNUMBER(R88),S88<>"",U88<>"",V88="Confirmat"),1,0) -> 0
A89: DB-030-EN | B89: DB-030 | C89: NOIR | D89: The Black Archive | E89: 10 | F89: The Keeper of the Final Page | G89: EN | H89: EN | I89: Scriere nouă | J89: Planificat | K89: De desemnat | L89: =Catalog_100!I31 -> 35000 | M89: =Catalog_100!J31 -> 46304 | N89: =Catalog_100!K31 -> 46322 | O89: =Catalog_100!L31 -> 46324 | P89: =Catalog_100!M31 -> 46326 | V89: Neconfirmat | W89: Fără ediție finală confirmată | X89: =IF(AND(J89="Publicat",Q89<>"",ISNUMBER(R89),S89<>"",U89<>"",V89="Confirmat"),1,0) -> 0
A90: DB-030-RO | B90: DB-030 | C90: NOIR | D90: The Black Archive | E90: 10 | F90: The Keeper of the Final Page | G90: RO | H90: EN | I90: Traducere EN→RO | J90: Planificat | K90: De desemnat | L90: =Catalog_100!I31 -> 35000 | M90: =Catalog_100!J31 -> 46304 | N90: =Catalog_100!K31 -> 46322 | O90: =Catalog_100!L31 -> 46324 | P90: =Catalog_100!M31 -> 46326 | V90: Neconfirmat | W90: Fără ediție finală confirmată | X90: =IF(AND(J90="Publicat",Q90<>"",ISNUMBER(R90),S90<>"",U90<>"",V90="Confirmat"),1,0) -> 0
A91: DB-030-DE | B91: DB-030 | C91: NOIR | D91: The Black Archive | E91: 10 | F91: The Keeper of the Final Page | G91: DE | H91: EN | I91: Traducere EN→DE | J91: Planificat | K91: De desemnat | L91: =Catalog_100!I31 -> 35000 | M91: =Catalog_100!J31 -> 46304 | N91: =Catalog_100!K31 -> 46322 | O91: =Catalog_100!L31 -> 46324 | P91: =Catalog_100!M31 -> 46326 | V91: Neconfirmat | W91: Fără ediție finală confirmată | X91: =IF(AND(J91="Publicat",Q91<>"",ISNUMBER(R91),S91<>"",U91<>"",V91="Confirmat"),1,0) -> 0
A92: DB-031-EN | B92: DB-031 | C92: NOIR | D92: The Borderland Files | E92: 1 | F92: The Border Inn | G92: EN | H92: EN | I92: Scriere nouă | J92: Planificat | K92: De desemnat | L92: =Catalog_100!I32 -> 35000 | M92: =Catalog_100!J32 -> 46304 | N92: =Catalog_100!K32 -> 46322 | O92: =Catalog_100!L32 -> 46324 | P92: =Catalog_100!M32 -> 46326 | V92: Neconfirmat | W92: Fără ediție finală confirmată | X92: =IF(AND(J92="Publicat",Q92<>"",ISNUMBER(R92),S92<>"",U92<>"",V92="Confirmat"),1,0) -> 0
A93: DB-031-RO | B93: DB-031 | C93: NOIR | D93: The Borderland Files | E93: 1 | F93: The Border Inn | G93: RO | H93: EN | I93: Traducere EN→RO | J93: Planificat | K93: De desemnat | L93: =Catalog_100!I32 -> 35000 | M93: =Catalog_100!J32 -> 46304 | N93: =Catalog_100!K32 -> 46322 | O93: =Catalog_100!L32 -> 46324 | P93: =Catalog_100!M32 -> 46326 | V93: Neconfirmat | W93: Fără ediție finală confirmată | X93: =IF(AND(J93="Publicat",Q93<>"",ISNUMBER(R93),S93<>"",U93<>"",V93="Confirmat"),1,0) -> 0
A94: DB-031-DE | B94: DB-031 | C94: NOIR | D94: The Borderland Files | E94: 1 | F94: The Border Inn | G94: DE | H94: EN | I94: Traducere EN→DE | J94: Planificat | K94: De desemnat | L94: =Catalog_100!I32 -> 35000 | M94: =Catalog_100!J32 -> 46304 | N94: =Catalog_100!K32 -> 46322 | O94: =Catalog_100!L32 -> 46324 | P94: =Catalog_100!M32 -> 46326 | V94: Neconfirmat | W94: Fără ediție finală confirmată | X94: =IF(AND(J94="Publicat",Q94<>"",ISNUMBER(R94),S94<>"",U94<>"",V94="Confirmat"),1,0) -> 0
A95: DB-032-EN | B95: DB-032 | C95: NOIR | D95: The Borderland Files | E95: 2 | F95: The Ferryman's Receipt | G95: EN | H95: EN | I95: Scriere nouă | J95: Planificat | K95: De desemnat | L95: =Catalog_100!I33 -> 35000 | M95: =Catalog_100!J33 -> 46304 | N95: =Catalog_100!K33 -> 46322 | O95: =Catalog_100!L33 -> 46324 | P95: =Catalog_100!M33 -> 46326 | V95: Neconfirmat | W95: Fără ediție finală confirmată | X95: =IF(AND(J95="Publicat",Q95<>"",ISNUMBER(R95),S95<>"",U95<>"",V95="Confirmat"),1,0) -> 0
A96: DB-032-RO | B96: DB-032 | C96: NOIR | D96: The Borderland Files | E96: 2 | F96: The Ferryman's Receipt | G96: RO | H96: EN | I96: Traducere EN→RO | J96: Planificat | K96: De desemnat | L96: =Catalog_100!I33 -> 35000 | M96: =Catalog_100!J33 -> 46304 | N96: =Catalog_100!K33 -> 46322 | O96: =Catalog_100!L33 -> 46324 | P96: =Catalog_100!M33 -> 46326 | V96: Neconfirmat | W96: Fără ediție finală confirmată | X96: =IF(AND(J96="Publicat",Q96<>"",ISNUMBER(R96),S96<>"",U96<>"",V96="Confirmat"),1,0) -> 0
A97: DB-032-DE | B97: DB-032 | C97: NOIR | D97: The Borderland Files | E97: 2 | F97: The Ferryman's Receipt | G97: DE | H97: EN | I97: Traducere EN→DE | J97: Planificat | K97: De desemnat | L97: =Catalog_100!I33 -> 35000 | M97: =Catalog_100!J33 -> 46304 | N97: =Catalog_100!K33 -> 46322 | O97: =Catalog_100!L33 -> 46324 | P97: =Catalog_100!M33 -> 46326 | V97: Neconfirmat | W97: Fără ediție finală confirmată | X97: =IF(AND(J97="Publicat",Q97<>"",ISNUMBER(R97),S97<>"",U97<>"",V97="Confirmat"),1,0) -> 0
A98: DB-033-EN | B98: DB-033 | C98: NOIR | D98: The Borderland Files | E98: 3 | F98: The Last Customs Seal | G98: EN | H98: EN | I98: Scriere nouă | J98: Planificat | K98: De desemnat | L98: =Catalog_100!I34 -> 35000 | M98: =Catalog_100!J34 -> 46304 | N98: =Catalog_100!K34 -> 46322 | O98: =Catalog_100!L34 -> 46324 | P98: =Catalog_100!M34 -> 46326 | V98: Neconfirmat | W98: Fără ediție finală confirmată | X98: =IF(AND(J98="Publicat",Q98<>"",ISNUMBER(R98),S98<>"",U98<>"",V98="Confirmat"),1,0) -> 0
A99: DB-033-RO | B99: DB-033 | C99: NOIR | D99: The Borderland Files | E99: 3 | F99: The Last Customs Seal | G99: RO | H99: EN | I99: Traducere EN→RO | J99: Planificat | K99: De desemnat | L99: =Catalog_100!I34 -> 35000 | M99: =Catalog_100!J34 -> 46304 | N99: =Catalog_100!K34 -> 46322 | O99: =Catalog_100!L34 -> 46324 | P99: =Catalog_100!M34 -> 46326 | V99: Neconfirmat | W99: Fără ediție finală confirmată | X99: =IF(AND(J99="Publicat",Q99<>"",ISNUMBER(R99),S99<>"",U99<>"",V99="Confirmat"),1,0) -> 0
A100: DB-033-DE | B100: DB-033 | C100: NOIR | D100: The Borderland Files | E100: 3 | F100: The Last Customs Seal | G100: DE | H100: EN | I100: Traducere EN→DE | J100: Planificat | K100: De desemnat | L100: =Catalog_100!I34 -> 35000 | M100: =Catalog_100!J34 -> 46304 | N100: =Catalog_100!K34 -> 46322 | O100: =Catalog_100!L34 -> 46324 | P100: =Catalog_100!M34 -> 46326 | V100: Neconfirmat | W100: Fără ediție finală confirmată | X100: =IF(AND(J100="Publicat",Q100<>"",ISNUMBER(R100),S100<>"",U100<>"",V100="Confirmat"),1,0) -> 0
...

Sheet Calendar
A1: Interval | B1: Livrabil | C1: Mastere EN cumulative | D1: Titluri trilingve cumulative | E1: Deadline | F1: Realizat — de completat | G1: Responsabil | H1: Observații
A2: 23–27 sept. | B2: Audit, canon, echipă, probe, finanțare | C2: 0 | D2: 0 | E2: 46292 | G2: De desemnat | H2: Scenariu condiționat de capacitate și finanțare
A3: 28 sept.–4 oct. | B3: 4 mastere pilot; scriere în paralel | C3: 4 | D3: 0 | E3: 46299 | G3: De desemnat | H3: Scenariu condiționat de capacitate și finanțare
A4: 5–11 oct. | B4: 17 existente + 20 noi; pilot trilingv | C4: 37 | D4: 4 | E4: 46306 | G4: De desemnat | H4: Scenariu condiționat de capacitate și finanțare
A5: 12–18 oct. | B5: 20 mastere noi; fond în traducere | C5: 57 | D5: 4 | E5: 46313 | G5: De desemnat | H5: Scenariu condiționat de capacitate și finanțare
A6: 19–25 oct. | B6: 77 mastere; 17 titluri trilingve | C6: 77 | D6: 17 | E6: 46320 | G6: De desemnat | H6: Scenariu condiționat de capacitate și finanțare
A7: 26 oct.–1 nov. | B7: 100 mastere; lot A disponibil | C7: 100 | D7: 37 | E7: 46327 | G7: De desemnat | H7: Scenariu condiționat de capacitate și finanțare
A8: 2–8 nov. | B8: Lot B trilingv | C8: 100 | D8: 57 | E8: 46334 | G8: De desemnat | H8: Scenariu condiționat de capacitate și finanțare
A9: 9–15 nov. | B9: Lot C trilingv | C9: 100 | D9: 77 | E9: 46341 | G9: De desemnat | H9: Scenariu condiționat de capacitate și finanțare
A10: 16–22 nov. | B10: Lot D trilingv | C10: 100 | D10: 92 | E10: 46348 | G10: De desemnat | H10: Scenariu condiționat de capacitate și finanțare
A11: 23–29 nov. | B11: 100 titluri până la 28.11 | C11: 100 | D11: 100 | E11: 46355 | G11: De desemnat | H11: Scenariu condiționat de capacitate și finanțare
A12: 30 nov.–1 dec. | B12: Audit și acceptare finală | C12: 100 | D12: 100 | E12: 46357 | G12: De desemnat | H12: Scenariu condiționat de capacitate și finanțare

Sheet Capacitate
A1: Activitate | B1: Volum | C1: Unitate | D1: Unități acceptate / oră | E1: Zile productive / persoană | F1: Ore productive / zi | G1: Ore necesare | H1: Echiv. persoane
A2: Scriere nouă acceptată | B2: =SUMIF(Catalog_100!F2:F101,"Nou",Catalog_100!I2:I101) -> 4440000 | C2: cuvinte | D2: 700 | E2: 25 | F2: 5 | G2: =B2/D2 -> 6342.8571 | H2: =ROUNDUP(G2/(E2*F2),0) -> 51
A3: Restructurare fond | B3: =SUMIF(Catalog_100!F2:F101,"Fond",Catalog_100!I2:I101) -> 979000 | C3: cuvinte | D3: 1000 | E3: 20 | F3: 5 | G3: =B3/D3 -> 979 | H3: =ROUNDUP(G3/(E3*F3),0) -> 10
A4: Editare EN | B4: =SUM(Catalog_100!I2:I101) -> 5419000 | C4: cuvinte | D4: 1500 | E4: 35 | F4: 5 | G4: =B4/D4 -> 3612.6667 | H4: =ROUNDUP(G4/(E4*F4),0) -> 21
A5: Corectură EN | B5: =SUM(Catalog_100!I2:I101) -> 5419000 | C5: cuvinte | D5: 2500 | E5: 35 | F5: 5 | G5: =B5/D5 -> 2167.6 | H5: =ROUNDUP(G5/(E5*F5),0) -> 13
A6: Traducere/posteditare | B6: =SUM(Catalog_100!I2:I101)*2 -> 10838000 | C6: cuvinte sursă | D6: 1000 | E6: 35 | F6: 5 | G6: =B6/D6 -> 10838 | H6: =ROUNDUP(G6/(E6*F6),0) -> 62
A7: Corectură traduceri | B7: =SUM(Catalog_100!I2:I101)*2 -> 10838000 | C7: cuvinte sursă | D7: 2500 | E7: 30 | F7: 5 | G7: =B7/D7 -> 4335.2 | H7: =ROUNDUP(G7/(E7*F7),0) -> 29
A8: Producție digitală | B8: =COUNTA(Editii_300!A2:A301) -> 300 | C8: ediții | D8: 0.16666667 | E8: 30 | F8: 5 | G8: =B8/D8 -> 1800 | H8: =ROUNDUP(G8/(E8*F8),0) -> 12
A9: QA final | B9: =COUNTA(Editii_300!A2:A301) -> 300 | C9: ediții | D9: 0.5 | E9: 25 | F9: 5 | G9: =B9/D9 -> 600 | H9: =ROUNDUP(G9/(E9*F9),0) -> 5
A11: TOTAL EXECUȚIE | H11: =SUM(H2:H9) -> 203
A13: Coordonare/design/marketing | H13: 12
A14: Total orientativ | H14: =H11+H13 -> 215
A16: Vitezele sunt ipoteze, nu standarde. Validare prin probe plătite. Persoanele nu pot fi numărate simultan în două roluri.
A19: Capacitate editorială. Dezvoltarea site-ului este un proiect separat; bugetul are doar o rezervă de integrare.

Sheet Buget
A1: Activitate | B1: Cantitate | C1: Tarif jos EUR | D1: Tarif bază EUR | E1: Tarif ridicat EUR | F1: Cost jos EUR | G1: Cost bază EUR | H1: Cost ridicat EUR | I1: Observație
A2: Scriere 83 titluri | B2: =SUMIF(Catalog_100!F2:F101,"Nou",Catalog_100!I2:I101) -> 4440000 | C2: 0.03 | D2: 0.06 | E2: 0.09 | F2: =B2*C2 -> 133200 | G2: =B2*D2 -> 266400 | H2: =B2*E2 -> 399600 | I2: Ipoteză; de înlocuit cu oferte
A3: Restructurare fond existent | B3: =SUMIF(Catalog_100!F2:F101,"Fond",Catalog_100!I2:I101) -> 979000 | C3: 0.006 | D3: 0.012 | E3: 0.02 | F3: =B3*C3 -> 5874 | G3: =B3*D3 -> 11748 | H3: =B3*E3 -> 19580 | I3: Ipoteză; de înlocuit cu oferte
A4: Editare EN | B4: =SUM(Catalog_100!I2:I101) -> 5419000 | C4: 0.01 | D4: 0.02 | E4: 0.03 | F4: =B4*C4 -> 54190 | G4: =B4*D4 -> 108380 | H4: =B4*E4 -> 162570 | I4: Ipoteză; de înlocuit cu oferte
A5: Corectură EN | B5: =SUM(Catalog_100!I2:I101) -> 5419000 | C5: 0.004 | D5: 0.008 | E5: 0.012 | F5: =B5*C5 -> 21676 | G5: =B5*D5 -> 43352 | H5: =B5*E5 -> 65028 | I5: Ipoteză; de înlocuit cu oferte
A6: Traducere / posteditare integrală | B6: =SUM(Catalog_100!I2:I101)*2 -> 10838000 | C6: 0.025 | D6: 0.05 | E6: 0.09 | F6: =B6*C6 -> 270950 | G6: =B6*D6 -> 541900 | H6: =B6*E6 -> 975420 | I6: Ipoteză; de înlocuit cu oferte
A7: Corectură independentă traduceri | B7: =SUM(Catalog_100!I2:I101)*2 -> 10838000 | C7: 0.006 | D7: 0.012 | E7: 0.018 | F7: =B7*C7 -> 65028 | G7: =B7*D7 -> 130056 | H7: =B7*E7 -> 195084 | I7: Ipoteză; de înlocuit cu oferte
A8: Design coperte originale | B8: =COUNTA(Catalog_100!A2:A101) -> 100 | C8: 200 | D8: 400 | E8: 700 | F8: =B8*C8 -> 20000 | G8: =B8*D8 -> 40000 | H8: =B8*E8 -> 70000 | I8: Ipoteză; de înlocuit cu oferte
A9: Localizare coperte | B9: =COUNTA(Catalog_100!A2:A101)*2 -> 200 | C9: 40 | D9: 75 | E9: 120 | F9: =B9*C9 -> 8000 | G9: =B9*D9 -> 15000 | H9: =B9*E9 -> 24000 | I9: Ipoteză; de înlocuit cu oferte
A10: EPUB și metadate | B10: =COUNTA(Editii_300!A2:A301) -> 300 | C10: 60 | D10: 120 | E10: 180 | F10: =B10*C10 -> 18000 | G10: =B10*D10 -> 36000 | H10: =B10*E10 -> 54000 | I10: Ipoteză; de înlocuit cu oferte
A11: QA final | B11: =COUNTA(Editii_300!A2:A301) -> 300 | C11: 20 | D11: 40 | E11: 60 | F11: =B11*C11 -> 6000 | G11: =B11*D11 -> 12000 | H11: =B11*E11 -> 18000 | I11: Ipoteză; de înlocuit cu oferte
A12: Coordonare/drepturi/administrare | B12: 1 | C12: 18000 | D12: 35000 | E12: 60000 | F12: =B12*C12 -> 18000 | G12: =B12*D12 -> 35000 | H12: =B12*E12 -> 60000 | I12: Ipoteză; de înlocuit cu oferte
A13: Comerț online și infrastructură | B13: 1 | C13: 5000 | D13: 12000 | E13: 20000 | F13: =B13*C13 -> 5000 | G13: =B13*D13 -> 12000 | H13: =B13*E13 -> 20000 | I13: Ipoteză; de înlocuit cu oferte
A14: Marketing test și lansare | B14: 1 | C14: 10000 | D14: 25000 | E14: 50000 | F14: =B14*C14 -> 10000 | G14: =B14*D14 -> 25000 | H14: =B14*E14 -> 50000 | I14: Ipoteză; de înlocuit cu oferte
A16: SUBTOTAL | F16: =SUM(F2:F14) -> 635918 | G16: =SUM(G2:G14) -> 1276836 | H16: =SUM(H2:H14) -> 2113282
A17: Rezervă | B17: 0.2 | F17: =F16*$B$17 -> 127183.6 | G17: =G16*$B$17 -> 255367.2 | H17: =H16*$B$17 -> 422656.4
A18: TOTAL CU REZERVĂ | F18: =F16+F17 -> 763101.6 | G18: =G16+G17 -> 1532203.2 | H18: =H16+H17 -> 2535938.4
A21: Fără taxe pe facturi, print/stoc sau audio. Rate ipotetice, nu oferte. Nu adăugați salariile aceleiași prestații peste tariful pe cuvânt.

Sheet Scenarii
A1: MODEL DE ABONAMENT — IPOTEZE, NU PROGNOZE
A2: Preț brut RON / lună | B2: 100 | C2: Tarif comunicat de beneficiar; Reader 10.
A3: Titluri deblocate lunar | B3: 10 | C3: Acces cât abonamentul este activ.
A4: Cotă taxă ipotetică | B4: 0.21 | C4: Sensibilitate, NU încadrare fiscală. Confirmați cu contabilul.
A5: Procesare plată RON | B5: 3 | C5: Ipoteză, nu ofertă de procesator.
A6: Cost variabil RON | B6: 8 | C6: Suport/infrastructură; de măsurat.
A7: Rezervă drepturi / net | B7: 0.1 | C7: Ipoteză contractuală.
A8: Cost fix lunar RON | B8: 30000 | C8: Nu include producția catalogului, marketingul sau noile titluri.
A9: Retenție lunară ipotetică | B9: 0.9 | C9: Se înlocuiește cu date de cohortă.
A10: Plafon CAC de test RON | B10: 60 | C10: Regulă conservatoare inițială, nu cost măsurat.
A11: Curs de planificare RON/EUR | B11: 5 | C11: NU cotație live și nu tarif de conversie pentru site.
A13: Venit net RON | B13: =B2/(1+B4) -> 82.644628
A14: Contribuție / abonat RON | B14: =B13*(1-B7)-B5-B6 -> 63.380165
A15: Prag operațional abonați | B15: =IF(B14>0,ROUNDUP(B8/B14,0),0) -> 474 | C15: Fără marketing, recuperarea catalogului și investiții viitoare; zero dacă marja este negativă nu înseamnă fezabilitate.
A16: Contribuție 6 luni estimată | B16: =B14*(1+B9+B9^2+B9^3+B9^4+B9^5) -> 296.97347
A17: O treime din contribuția 6 luni | B17: =B16/3 -> 98.991156
A18: Catalog bază RON | B18: =Buget!G18*B11 -> 7661016
A19: Luni-abonat pentru catalog | B19: =IF(B14>0,B18/B14,0) -> 120874.03 | C19: Înainte de cost fix și achiziție. NU durată de recuperare și NU abonați existenți.
A21: Abonați activi | B21: Încasări brute | C21: Contribuție | D21: După cost fix | E21: Luni recuperare înainte de CAC/noi cărți
A22: 200 | B22: =A22*$B$2 -> 20000 | C22: =A22*$B$14 -> 12676.033 | D22: =C22-$B$8 -> -17323.967 | E22: =IF(D22>0,$B$18/D22,0) -> 0
A23: 1000 | B23: =A23*$B$2 -> 100000 | C23: =A23*$B$14 -> 63380.165 | D23: =C23-$B$8 -> 33380.165 | E23: =IF(D23>0,$B$18/D23,0) -> 229.50803
A24: 3000 | B24: =A24*$B$2 -> 300000 | C24: =A24*$B$14 -> 190140.5 | D24: =C24-$B$8 -> 160140.5 | E24: =IF(D24>0,$B$18/D24,0) -> 47.839342
A25: 10000 | B25: =A25*$B$2 -> 1000000 | C25: =A25*$B$14 -> 633801.65 | D25: =C25-$B$8 -> 603801.65 | E25: =IF(D25>0,$B$18/D25,0) -> 12.687968
A27: 0 la recuperare = nerecuperabil în scenariul cu marjă operațională <= 0; nu înseamnă recuperare instantanee.

Sheet KPI
A1: Indicator | B1: Definiție | C1: Ipoteză / prag | D1: Interpretare | E1: Realizat
A2: Conversie abonat | B2: Plătitori noi / vizite calificate | C2: 0.02 | D2: Ipoteză, per limbă/canal
A3: Activare 72h | B3: Abonați care încep prima carte / abonați noi | C3: 0.6 | D3: Obiectiv de test
A4: Trecere vol.1→vol.2 | B4: Cititori vol.1 care încep vol.2 | C4: 0.35 | D4: Obiectiv de test; definiție cohortă consecventă
A5: Retenție lunară | B5: Reînnoiri / abonamente eligibile | C5: 0.9 | D5: Ipoteză; primul semnal abia la sfârșit de noiembrie
A6: CAC | B6: Cheltuieli de achiziție / abonați noi | C6: 60 | D6: RON; plafon inițial, nu rezultat
A7: Defecte critice | B7: Capitole lipsă / drepturi / traducere / acces | C7: 0 | D7: Prag obligatoriu înainte de lansare

Sheet Surse
A1: ID | B1: Sursă | C1: URL | D1: Utilizare / limită
A2: S1 | B2: AAP — StatShot Annual 2025 (10.08.2026) | C2: https://publishers.org/news/aap-statshot-annual-report-publishing-revenues-totaled-33-4-billion-for-calendar-year-2025/ | D2: Piața SUA: venituri, ficțiune adulți, copii/YA.
A3: S2 | B3: Börsenverein — bilanț 2025 (09.07.2026) | C3: https://www.boersenverein.de/presse/pressemitteilungen/detailseite/lesekompetenz-sinkt-handlungsbedarf-waechst-junge-menschen-kaufen-weniger-buecher/ | D3: Piața germană și dinamica genurilor.
A4: S3 | B4: Circana — Romance with a Dark Twist (iunie 2025) | C4: https://www.circana.com/post/another-year-of-romance-with-a-dark-twist-circana-bookscan-reports | D4: Date de print romance SUA; nu prognoză pentru 2026.
A5: S4 | B5: Publishers Association — Publishing in 2025 | C5: https://www.publishers.org.uk/publications/publishing-in-2025/ | D5: Structura pieței britanice; print consumer 79%.
A6: S5 | B6: Forbes România — Top 101 edituri, bilanțuri 2025 | C6: https://www.forbes.ro/exclusiv-top-101-edituri-din-romania-cu-bilanturile-financiare-in-anul-2025-508709 | D6: Sursă secundară; eșantion de edituri, nu întreaga piață retail.
A7: S6 | B7: Eurostat — reading books in the EU (09.08.2024) | C7: https://ec.europa.eu/eurostat/web/products-eurostat-news/w/ddn-20240809-2 | D7: Date pentru anul 2022; comportament de lectură, nu abonare.
A8: S7 | B8: Freida McFadden — The Housemaid series | C8: https://www.freidamcfadden.com/books/the-housemaid-series/ | D8: Reper oficial de prezentare a seriei, nu date de conversie.
A9: S8 | B9: Penguin Random House — Funny Story | C9: https://www.penguinrandomhouse.com/books/704945/funny-story-by-emily-henry/ | D9: Reper oficial de prezentare a premisei.
A10: S9 | B10: Pan Macmillan — Crowns of Nyaxia | C10: https://www.panmacmillan.com/series/crowns-of-nyaxia/panmac84652 | D10: Reper oficial de structurare a universului.
A11: S10 | B11: KDP — Content Guidelines / AI-generated content | C11: https://kdp.amazon.com/en_US/help/topic/G200672390 | D11: Declararea conținutului generat AI.
A12: S11 | B12: KDP — Create a Book / title creation limits | C12: https://kdp.amazon.com/en_US/help/topic/G202172740 | D12: Verificare directă 23.09: 2 titluri/format/săptămână; versiuni indexate contradictorii.
... A19: S23 | B19: Skoobe — Wie viel kostet ein Skoobe-Abo? (07.09.2026) | C19: https://support.skoobe.de/hc/de/articles/360015307380-Wie-viel-kostet-ein-Skoobe-Abo | D19: Basic 12,99 EUR/30 zile; Standard 14,99.
